<?xml version="1.0" ?>
<annotation>
  <folder>images</folder>
  <filename>73_0_00073</filename>
  <path>data_augmentation/73_0_00073.jpg</path>
  <source>
    <database>Unknown</database>
  </source>
  <size>
    <width>640</width>
    <height>640</height>
    <depth>3</depth>
  </size>
  <segmented>0</segmented>
  <object>
    <name>T_L_R</name>
    <pose>Unspecified</pose>
    <truncated>0</truncated>
    <difficult>0</difficult>
    <confidence>1.0</confidence>
    <bndbox>
      <xmin>421</xmin>
      <ymin>383</ymin>
      <xmax>577</xmax>
      <ymax>534</ymax>
    </bndbox>
  </object>
  <object>
    <name>T_L_R</name>
    <pose>Unspecified</pose>
    <truncated>0</truncated>
    <difficult>0</difficult>
    <confidence>1.0</confidence>
    <bndbox>
      <xmin>121</xmin>
      <ymin>94</ymin>
      <xmax>270</xmax>
      <ymax>258</ymax>
    </bndbox>
  </object>
  <object>
    <name>T_L_R</name>
    <pose>Unspecified</pose>
    <truncated>0</truncated>
    <difficult>0</difficult>
    <confidence>1.0</confidence>
    <bndbox>
      <xmin>395</xmin>
      <ymin>203</ymin>
      <xmax>514</xmax>
      <ymax>271</ymax>
    </bndbox>
  </object>
  <object>
    <name>T_L_R</name>
    <pose>Unspecified</pose>
    <truncated>0</truncated>
    <difficult>0</difficult>
    <confidence>1.0</confidence>
    <bndbox>
      <xmin>379</xmin>
      <ymin>403</ymin>
      <xmax>419</xmax>
      <ymax>514</ymax>
    </bndbox>
  </object>
  <object>
    <name>T_L_R</name>
    <pose>Unspecified</pose>
    <truncated>0</truncated>
    <difficult>0</difficult>
    <confidence>1.0</confidence>
    <bndbox>
      <xmin>405</xmin>
      <ymin>323</ymin>
      <xmax>486</xmax>
      <ymax>401</ymax>
    </bndbox>
  </object>
  <object>
    <name>T_L_R</name>
    <pose>Unspecified</pose>
    <truncated>0</truncated>
    <difficult>0</difficult>
    <confidence>1.0</confidence>
    <bndbox>
      <xmin>282</xmin>
      <ymin>153</ymin>
      <xmax>320</xmax>
      <ymax>254</ymax>
    </bndbox>
  </object>
  <object>
    <name>T_L_R</name>
    <pose>Unspecified</pose>
    <truncated>0</truncated>
    <difficult>0</difficult>
    <confidence>1.0</confidence>
    <bndbox>
      <xmin>226</xmin>
      <ymin>236</ymin>
      <xmax>291</xmax>
      <ymax>292</ymax>
    </bndbox>
  </object>
  <object>
    <name>T_L_R</name>
    <pose>Unspecified</pose>
    <truncated>0</truncated>
    <difficult>0</difficult>
    <confidence>1.0</confidence>
    <bndbox>
      <xmin>326</xmin>
      <ymin>369</ymin>
      <xmax>375</xmax>
      <ymax>456</ymax>
    </bndbox>
  </object>
  <object>
    <name>T_L_R</name>
    <pose>Unspecified</pose>
    <truncated>0</truncated>
    <difficult>0</difficult>
    <confidence>1.0</confidence>
    <bndbox>
      <xmin>371</xmin>
      <ymin>284</ymin>
      <xmax>432</xmax>
      <ymax>371</ymax>
    </bndbox>
  </object>
  <object>
    <name>T_L_R</name>
    <pose>Unspecified</pose>
    <truncated>0</truncated>
    <difficult>0</difficult>
    <confidence>1.0</confidence>
    <bndbox>
      <xmin>266</xmin>
      <ymin>163</ymin>
      <xmax>290</xmax>
      <ymax>236</ymax>
    </bndbox>
  </object>
</annotation>
