<annotation>
	<folder></folder>
	<filename>00035_jpg.rf.9295deed97d363e1dec906aaf3e9534e.jpg</filename>
	<path>00035_jpg.rf.9295deed97d363e1dec906aaf3e9534e.jpg</path>
	<source>
		<database>roboflow.com</database>
	</source>
	<size>
		<width>416</width>
		<height>416</height>
		<depth>3</depth>
	</size>
	<segmented>0</segmented>
	<object>
		<name>T_L_R</name>
		<pose>Unspecified</pose>
		<truncated>0</truncated>
		<difficult>0</difficult>
		<occluded>0</occluded>
		<bndbox>
			<xmin>136</xmin>
			<xmax>172</xmax>
			<ymin>126</ymin>
			<ymax>222</ymax>
		</bndbox>
		<polygon>
			<x1>161.6875</x1>
			<y1>201.567708</y1>
			<x2>166.5625</x2>
			<y2>192.765625</y2>
			<x3>167.375</x3>
			<y3>178.682292</y3>
			<x4>171.4375</x4>
			<y4>171.640625</y4>
			<x5>171.4375</x5>
			<y5>166.359375</y5>
			<x6>168.1875</x6>
			<y6>148.755208</y6>
			<x7>163.71875</x7>
			<y7>140.833333</y7>
			<x8>158.03125</x8>
			<y8>140.833333</y8>
			<x9>156</x9>
			<y9>136.432292</y9>
			<x10>155.1875</x10>
			<y10>129.390625</y10>
			<x11>152.34375</x11>
			<y11>124.989583</y11>
			<x12>149.09375</x12>
			<y12>124.989583</y12>
			<x13>147.46875</x13>
			<y13>130.270833</y13>
			<x14>144.21875</x14>
			<y14>132.03125</y14>
			<x15>140.5625</x15>
			<y15>139.953125</y15>
			<x16>140.5625</x16>
			<y16>146.994792</y16>
			<x17>138.9375</x17>
			<y17>154.036459</y17>
			<x18>138.9375</x18>
			<y18>168.119792</y18>
			<x19>135.6875</x19>
			<y19>173.401042</y19>
			<x20>134.875</x20>
			<y20>198.046875</y20>
			<x21>137.3125</x21>
			<y21>205.088542</y21>
			<x22>138.125</x22>
			<y22>215.651042</y22>
			<x23>140.15625</x23>
			<y23>220.052083</y23>
			<x24>143</x24>
			<y24>220.932292</y24>
			<x25>150.71875</x25>
			<y25>220.052083</y25>
			<x26>153.15625</x26>
			<y26>216.53125</y26>
			<x27>158.03125</x27>
			<y27>214.770833</y27>
			<x28>161.6875</x28>
			<y28>201.567708</y28>
		</polygon>
	</object>
	<object>
		<name>T_L_R</name>
		<pose>Unspecified</pose>
		<truncated>0</truncated>
		<difficult>0</difficult>
		<occluded>0</occluded>
		<bndbox>
			<xmin>164</xmin>
			<xmax>198</xmax>
			<ymin>47</ymin>
			<ymax>116</ymax>
		</bndbox>
		<polygon>
			<x1>195.8125</x1>
			<y1>78.338542</y1>
			<x2>197.4375</x2>
			<y2>74.817708</y2>
			<x3>197.4375</x3>
			<y3>69.536459</y3>
			<x4>196.625</x4>
			<y4>60.734375</y4>
			<x5>190.53125</x5>
			<y5>51.052083</y5>
			<x6>184.03125</x6>
			<y6>47.53125</y6>
			<x7>179.15625</x7>
			<y7>49.291666</y7>
			<x8>175.09375</x8>
			<y8>45.770833</y8>
			<x9>171.03125</x9>
			<y9>52.8125</y9>
			<x10>168.59375</x10>
			<y10>52.8125</y10>
			<x11>162.5</x11>
			<y11>66.015625</y11>
			<x12>165.75</x12>
			<y12>85.380208</y12>
			<x13>169</x13>
			<y13>92.421875</y13>
			<x14>168.1875</x14>
			<y14>101.223958</y14>
			<x15>170.625</x15>
			<y15>104.744792</y15>
			<x16>173.46875</x16>
			<y16>114.427083</y16>
			<x17>179.5625</x17>
			<y17>115.307291</y17>
			<x18>183.21875</x18>
			<y18>112.666667</y18>
			<x19>192.5625</x19>
			<y19>97.703125</y19>
			<x20>196.625</x20>
			<y20>85.380208</y20>
			<x21>195.8125</x21>
			<y21>78.338542</y21>
		</polygon>
	</object>
	<object>
		<name>T_L_R</name>
		<pose>Unspecified</pose>
		<truncated>0</truncated>
		<difficult>0</difficult>
		<occluded>0</occluded>
		<bndbox>
			<xmin>205</xmin>
			<xmax>236</xmax>
			<ymin>247</ymin>
			<ymax>336</ymax>
		</bndbox>
		<polygon>
			<x1>227.5</x1>
			<y1>303.671875</y1>
			<x2>234.8125</x2>
			<y2>280.786459</y2>
			<x3>230.75</x3>
			<y3>264.942709</y3>
			<x4>227.90625</x4>
			<y4>258.78125</y4>
			<x5>223.03125</x5>
			<y5>255.260417</y5>
			<x6>218.96875</x6>
			<y6>246.458333</y6>
			<x7>215.71875</x7>
			<y7>246.458333</y7>
			<x8>213.6875</x8>
			<y8>250.859375</y8>
			<x9>214.5</x9>
			<y9>256.140625</y9>
			<x10>206.375</x10>
			<y10>273.744792</y10>
			<x11>208</x11>
			<y11>279.026042</y11>
			<x12>208</x12>
			<y12>286.067708</y12>
			<x13>207.1875</x13>
			<y13>293.109375</y13>
			<x14>205.5625</x14>
			<y14>296.630208</y14>
			<x15>205.5625</x15>
			<y15>310.713541</y15>
			<x16>203.9375</x16>
			<y16>324.796875</y16>
			<x17>203.9375</x17>
			<y17>333.598958</y17>
			<x18>205.5625</x18>
			<y18>335.359375</y18>
			<x19>218.15625</x19>
			<y19>325.677083</y19>
			<x20>223.84375</x20>
			<y20>315.114584</y20>
			<x21>226.28125</x21>
			<y21>316.875</y21>
			<x22>227.5</x22>
			<y22>303.671875</y22>
		</polygon>
	</object>
	<object>
		<name>T_L_R</name>
		<pose>Unspecified</pose>
		<truncated>0</truncated>
		<difficult>0</difficult>
		<occluded>0</occluded>
		<bndbox>
			<xmin>255</xmin>
			<xmax>277</xmax>
			<ymin>281</ymin>
			<ymax>354</ymax>
		</bndbox>
		<polygon>
			<x1>275.4375</x1>
			<y1>298.390625</y1>
			<x2>273.8125</x2>
			<y2>293.109375</y2>
			<x3>273.8125</x3>
			<y3>284.307291</y3>
			<x4>272.59375</x4>
			<y4>281.666667</y4>
			<x5>257.96875</x5>
			<y5>279.90625</y5>
			<x6>254.3125</x6>
			<y6>289.588542</y6>
			<x7>255.125</x7>
			<y7>296.630208</y7>
			<x8>254.3125</x8>
			<y8>314.234375</y8>
			<x9>255.9375</x9>
			<y9>317.755208</y9>
			<x10>255.9375</x10>
			<y10>330.078125</y10>
			<x11>259.1875</x11>
			<y11>344.161458</y11>
			<x12>263.65625</x12>
			<y12>352.083333</y12>
			<x13>266.5</x13>
			<y13>352.963541</y13>
			<x14>271.375</x14>
			<y14>342.401042</y14>
			<x15>273.8125</x15>
			<y15>319.515625</y15>
			<x16>276.25</x16>
			<y16>312.473958</y16>
			<x17>275.4375</x17>
			<y17>298.390625</y17>
		</polygon>
	</object>
	<object>
		<name>T_L_R</name>
		<pose>Unspecified</pose>
		<truncated>0</truncated>
		<difficult>0</difficult>
		<occluded>0</occluded>
		<bndbox>
			<xmin>278</xmin>
			<xmax>306</xmax>
			<ymin>233</ymin>
			<ymax>308</ymax>
		</bndbox>
		<polygon>
			<x1>301.4375</x1>
			<y1>282.546875</y1>
			<x2>303.0625</x2>
			<y2>277.265625</y2>
			<x3>303.0625</x3>
			<y3>266.703125</y3>
			<x4>304.6875</x4>
			<y4>252.619792</y4>
			<x5>304.6875</x5>
			<y5>245.578125</y5>
			<x6>301.84375</x6>
			<y6>235.895833</y6>
			<x7>298.59375</x7>
			<y7>237.65625</y7>
			<x8>296.15625</x8>
			<y8>232.375</y8>
			<x9>288.03125</x9>
			<y9>234.135416</y9>
			<x10>283.96875</x10>
			<y10>244.697917</y10>
			<x11>279.90625</x11>
			<y11>244.697917</y11>
			<x12>277.875</x12>
			<y12>252.619792</y12>
			<x13>277.0625</x13>
			<y13>257.901042</y13>
			<x14>277.875</x14>
			<y14>263.182292</y14>
			<x15>281.9375</x15>
			<y15>277.265625</y15>
			<x16>278.6875</x16>
			<y16>286.067708</y16>
			<x17>278.6875</x17>
			<y17>289.588542</y17>
			<x18>283.96875</x18>
			<y18>301.03125</y18>
			<x19>289.25</x19>
			<y19>307.192709</y19>
			<x20>293.71875</x20>
			<y20>299.270833</y20>
			<x21>298.59375</x21>
			<y21>299.270833</y21>
			<x22>301.4375</x22>
			<y22>294.869792</y22>
			<x23>301.4375</x23>
			<y23>282.546875</y23>
		</polygon>
	</object>
	<object>
		<name>T_L_R</name>
		<pose>Unspecified</pose>
		<truncated>0</truncated>
		<difficult>0</difficult>
		<occluded>0</occluded>
		<bndbox>
			<xmin>212</xmin>
			<xmax>242</xmax>
			<ymin>61</ymin>
			<ymax>171</ymax>
		</bndbox>
		<polygon>
			<x1>238.0625</x1>
			<y1>113.546875</y1>
			<x2>234.8125</x2>
			<y2>110.026042</y2>
			<x3>235.625</x3>
			<y3>97.703125</y3>
			<x4>233.1875</x4>
			<y4>87.140625</y4>
			<x5>228.3125</x5>
			<y5>76.578125</y5>
			<x6>227.5</x6>
			<y6>66.015625</y6>
			<x7>225.46875</x7>
			<y7>59.854167</y7>
			<x8>221</x8>
			<y8>74.817708</y8>
			<x9>221</x9>
			<y9>85.380208</y9>
			<x10>219.375</x10>
			<y10>88.901042</y10>
			<x11>220.1875</x11>
			<y11>106.505208</y11>
			<x12>217.34375</x12>
			<y12>107.385416</y12>
			<x13>216.53125</x13>
			<y13>105.625</y13>
			<x14>214.5</x14>
			<y14>108.265625</y14>
			<x15>216.125</x15>
			<y15>113.546875</y15>
			<x16>216.125</x16>
			<y16>120.588542</y16>
			<x17>211.25</x17>
			<y17>129.390625</y17>
			<x18>213.6875</x18>
			<y18>136.432292</y18>
			<x19>213.6875</x19>
			<y19>143.473958</y19>
			<x20>215.3125</x20>
			<y20>148.755208</y20>
			<x21>214.5</x21>
			<y21>152.276042</y21>
			<x22>221.40625</x22>
			<y22>167.239583</y22>
			<x23>224.65625</x23>
			<y23>169</y23>
			<x24>227.09375</x24>
			<y24>163.71875</y24>
			<x25>229.53125</x25>
			<y25>169</y25>
			<x26>233.1875</x26>
			<y26>169.880208</y26>
			<x27>236.4375</x27>
			<y27>166.359375</y27>
			<x28>241.3125</x28>
			<y28>141.713541</y28>
			<x29>238.875</x29>
			<y29>138.192709</y29>
			<x30>238.0625</x30>
			<y30>113.546875</y30>
		</polygon>
	</object>
	<object>
		<name>T_L_H</name>
		<pose>Unspecified</pose>
		<truncated>0</truncated>
		<difficult>0</difficult>
		<occluded>0</occluded>
		<bndbox>
			<xmin>3</xmin>
			<xmax>107</xmax>
			<ymin>309</ymin>
			<ymax>416</ymax>
		</bndbox>
		<polygon>
			<x1>99.9375</x1>
			<y1>367.046875</y1>
			<x2>91.40625</x2>
			<y2>357.364584</y2>
			<x3>82.46875</x3>
			<y3>336.239583</y3>
			<x4>80.03125</x4>
			<y4>334.479167</y4>
			<x5>75.96875</x5>
			<y5>338</y5>
			<x6>69.46875</x6>
			<y6>320.395833</y6>
			<x7>58.90625</x7>
			<y7>308.072917</y7>
			<x8>54.03125</x8>
			<y8>308.072917</y8>
			<x9>51.59375</x9>
			<y9>313.354167</y9>
			<x10>45.09375</x10>
			<y10>313.354167</y10>
			<x11>44.28125</x11>
			<y11>311.59375</y11>
			<x12>36.15625</x12>
			<y12>313.354167</y12>
			<x13>32.09375</x13>
			<y13>323.916667</y13>
			<x14>19.90625</x14>
			<y14>332.71875</y14>
			<x15>6.90625</x15>
			<y15>352.083333</y15>
			<x16>4.0625</x16>
			<y16>360.005208</y16>
			<x17>1.625</x17>
			<y17>375.848958</y17>
			<x18>2.4375</x18>
			<y18>391.692709</y18>
			<x19>6.09375</x19>
			<y19>399.614584</y19>
			<x20>12.59375</x20>
			<y20>403.135416</y20>
			<x21>20.71875</x21>
			<y21>413.697917</y21>
			<x22>50.78125</x22>
			<y22>415.458333</y22>
			<x23>56.46875</x23>
			<y23>411.9375</y23>
			<x24>57.28125</x24>
			<y24>413.697917</y24>
			<x25>62.96875</x25>
			<y25>411.9375</y25>
			<x26>68.65625</x26>
			<y26>415.458333</y26>
			<x27>102.375</x27>
			<y27>414.578125</y27>
			<x28>104.8125</x28>
			<y28>405.776042</y28>
			<x29>105.625</x29>
			<y29>386.411458</y29>
			<x30>99.9375</x30>
			<y30>375.848958</y30>
			<x31>99.9375</x31>
			<y31>367.046875</y31>
		</polygon>
	</object>
</annotation>
