<annotation>
	<folder></folder>
	<filename>00230_jpg.rf.ef72fd9679992f448666e51a3f660d8e.jpg</filename>
	<path>00230_jpg.rf.ef72fd9679992f448666e51a3f660d8e.jpg</path>
	<source>
		<database>roboflow.com</database>
	</source>
	<size>
		<width>416</width>
		<height>416</height>
		<depth>3</depth>
	</size>
	<segmented>0</segmented>
	<object>
		<name>T_L_R</name>
		<pose>Unspecified</pose>
		<truncated>0</truncated>
		<difficult>0</difficult>
		<occluded>0</occluded>
		<bndbox>
			<xmin>80</xmin>
			<xmax>187</xmax>
			<ymin>262</ymin>
			<ymax>389</ymax>
		</bndbox>
		<polygon>
			<x1>101.833333</x1>
			<y1>366.84375</y1>
			<x2>102.916667</x2>
			<y2>363.59375</y2>
			<x3>107.791667</x3>
			<y3>360.75</y3>
			<x4>115.916667</x4>
			<y4>353.84375</y4>
			<x5>117</x5>
			<y5>351.40625</y5>
			<x6>123.5</x6>
			<y6>344.09375</y6>
			<x7>127.291667</x7>
			<y7>341.25</y7>
			<x8>129.458333</x8>
			<y8>341.25</y8>
			<x9>130</x9>
			<y9>344.90625</y9>
			<x10>131.625</x10>
			<y10>345.3125</y10>
			<x11>134.333333</x11>
			<y11>342.46875</y11>
			<x12>134.333333</x12>
			<y12>340.84375</y12>
			<x13>138.666667</x13>
			<y13>337.59375</y13>
			<x14>141.375</x14>
			<y14>333.9375</y14>
			<x15>144.083333</x15>
			<y15>335.15625</y15>
			<x16>145.166667</x16>
			<y16>337.59375</y16>
			<x17>148.958333</x17>
			<y17>341.25</y17>
			<x18>151.125</x18>
			<y18>340.4375</y18>
			<x19>152.75</x19>
			<y19>337.59375</y19>
			<x20>156</x20>
			<y20>335.15625</y20>
			<x21>160.333333</x21>
			<y21>327.84375</y21>
			<x22>161.958333</x22>
			<y22>326.625</y22>
			<x23>163.041667</x23>
			<y23>327.4375</y23>
			<x24>165.208333</x24>
			<y24>327.4375</y24>
			<x25>167.916667</x25>
			<y25>325.40625</y25>
			<x26>169</x26>
			<y26>321.34375</y26>
			<x27>170.083333</x27>
			<y27>320.53125</y27>
			<x28>170.083333</x28>
			<y28>313.21875</y28>
			<x29>171.708333</x29>
			<y29>312</y29>
			<x30>174.958333</x30>
			<y30>312</y30>
			<x31>178.75</x31>
			<y31>308.34375</y31>
			<x32>179.833333</x32>
			<y32>302.65625</y32>
			<x33>182</x33>
			<y33>298.59375</y33>
			<x34>180.916667</x34>
			<y34>296.15625</y34>
			<x35>184.166667</x35>
			<y35>294.53125</y35>
			<x36>186.333333</x36>
			<y36>291.28125</y36>
			<x37>186.333333</x37>
			<y37>282.34375</y37>
			<x38>185.25</x38>
			<y38>281.53125</y38>
			<x39>185.25</x39>
			<y39>279.90625</y39>
			<x40>183.083333</x40>
			<y40>277.46875</y40>
			<x41>173.875</x41>
			<y41>271.375</y41>
			<x42>169.541667</x42>
			<y42>270.5625</y42>
			<x43>166.291667</x43>
			<y43>272.1875</y43>
			<x44>164.125</x44>
			<y44>272.1875</y44>
			<x45>159.791667</x45>
			<y45>267.3125</y45>
			<x46>146.791667</x46>
			<y46>260.8125</y46>
			<x47>128.375</x47>
			<y47>261.625</y47>
			<x48>127.291667</x48>
			<y48>262.4375</y48>
			<x49>125.125</x49>
			<y49>262.4375</y49>
			<x50>122.416667</x50>
			<y50>264.46875</y50>
			<x51>121.333333</x51>
			<y51>266.90625</y51>
			<x52>126.208333</x52>
			<y52>269.75</y52>
			<x53>129.458333</x53>
			<y53>269.75</y53>
			<x54>130.541667</x54>
			<y54>270.5625</y54>
			<x55>141.375</x55>
			<y55>270.5625</y55>
			<x56>144.625</x56>
			<y56>272.1875</y56>
			<x57>146.791667</x57>
			<y57>272.1875</y57>
			<x58>149.5</x58>
			<y58>275.03125</y58>
			<x59>147.875</x59>
			<y59>277.875</y59>
			<x60>144.625</x60>
			<y60>277.875</y60>
			<x61>140.291667</x61>
			<y61>275.4375</y61>
			<x62>133.791667</x62>
			<y62>274.625</y62>
			<x63>132.708333</x63>
			<y63>273.8125</y63>
			<x64>128.375</x64>
			<y64>273.8125</y64>
			<x65>127.291667</x65>
			<y65>273</y65>
			<x66>112.125</x66>
			<y66>273</y66>
			<x67>105.625</x67>
			<y67>269.75</y67>
			<x68>99.125</x68>
			<y68>269.75</y68>
			<x69>95.333333</x69>
			<y69>271.78125</y69>
			<x70>98.041667</x70>
			<y70>274.625</y70>
			<x71>100.208333</x71>
			<y71>275.4375</y71>
			<x72>105.625</x72>
			<y72>275.4375</y72>
			<x73>108.875</x73>
			<y73>277.0625</y73>
			<x74>111.041667</x74>
			<y74>277.0625</y74>
			<x75>121.333333</x75>
			<y75>283.15625</y75>
			<x76>114.291667</x76>
			<y76>283.5625</y76>
			<x77>113.208333</x77>
			<y77>284.375</y77>
			<x78>105.625</x78>
			<y78>285.1875</y78>
			<x79>104.541667</x79>
			<y79>286</y79>
			<x80>96.958333</x80>
			<y80>286</y80>
			<x81>94.791667</x81>
			<y81>285.1875</y81>
			<x82>93.708333</x82>
			<y82>286</y82>
			<x83>90.458333</x83>
			<y83>286</y83>
			<x84>86.125</x84>
			<y84>289.25</y84>
			<x85>82.875</x85>
			<y85>289.25</y85>
			<x86>79.083333</x86>
			<y86>290.46875</y86>
			<x87>79.625</x87>
			<y87>292.5</y87>
			<x88>83.958333</x88>
			<y88>294.125</y88>
			<x89>89.375</x89>
			<y89>294.9375</y89>
			<x90>95.333333</x90>
			<y90>297.78125</y90>
			<x91>95.333333</x91>
			<y91>299.40625</y91>
			<x92>90.458333</x92>
			<y92>301.4375</y92>
			<x93>81.25</x93>
			<y93>308.34375</y93>
			<x94>81.25</x94>
			<y94>310.78125</y94>
			<x95>82.333333</x95>
			<y95>311.59375</y95>
			<x96>82.333333</x96>
			<y96>317.28125</y96>
			<x97>87.75</x97>
			<y97>322.96875</y97>
			<x98>87.75</x98>
			<y98>333.53125</y98>
			<x99>86.666667</x99>
			<y99>334.34375</y99>
			<x100>86.666667</x100>
			<y100>357.90625</y100>
			<x101>85.583333</x101>
			<y101>358.71875</y101>
			<x102>85.583333</x102>
			<y102>380.65625</y102>
			<x103>84.5</x103>
			<y103>381.46875</y103>
			<x104>85.583333</x104>
			<y104>382.28125</y104>
			<x105>84.5</x105>
			<y105>383.09375</y105>
			<x106>84.5</x106>
			<y106>385.53125</y106>
			<x107>85.583333</x107>
			<y107>386.34375</y107>
			<x108>85.583333</x108>
			<y108>387.96875</y108>
			<x109>86.666667</x109>
			<y109>387.96875</y109>
			<x110>87.75</x110>
			<y110>386.34375</y110>
			<x111>87.75</x111>
			<y111>381.46875</y111>
			<x112>93.166667</x112>
			<y112>372.53125</y112>
			<x113>101.833333</x113>
			<y113>366.84375</y113>
		</polygon>
	</object>
	<object>
		<name>T_L_R</name>
		<pose>Unspecified</pose>
		<truncated>0</truncated>
		<difficult>0</difficult>
		<occluded>0</occluded>
		<bndbox>
			<xmin>208</xmin>
			<xmax>340</xmax>
			<ymin>246</ymin>
			<ymax>326</ymax>
		</bndbox>
		<polygon>
			<x1>327.708333</x1>
			<y1>310.375</y1>
			<x2>326.083333</x2>
			<y2>308.34375</y2>
			<x3>327.166667</x3>
			<y3>301.84375</y3>
			<x4>323.916667</x4>
			<y4>297.78125</y4>
			<x5>313.083333</x5>
			<y5>288.84375</y5>
			<x6>313.083333</x6>
			<y6>288.03125</y6>
			<x7>309.833333</x7>
			<y7>286.40625</y7>
			<x8>305.5</x8>
			<y8>279.90625</y8>
			<x9>292.5</x9>
			<y9>269.34375</y9>
			<x10>292.5</x10>
			<y10>267.71875</y10>
			<x11>293.583333</x11>
			<y11>266.90625</y11>
			<x12>292.5</x12>
			<y12>265.28125</y12>
			<x13>288.708333</x13>
			<y13>263.25</y13>
			<x14>286.541667</x14>
			<y14>263.25</y14>
			<x15>267.583333</x15>
			<y15>249.03125</y15>
			<x16>265.958333</x16>
			<y16>247</y16>
			<x17>261.625</x17>
			<y17>246.1875</y17>
			<x18>260.541667</x18>
			<y18>247</y18>
			<x19>254.041667</x19>
			<y19>247</y19>
			<x20>249.708333</x20>
			<y20>248.625</y20>
			<x21>244.291667</x21>
			<y21>246.1875</y21>
			<x22>233.458333</x22>
			<y22>246.1875</y22>
			<x23>232.375</x23>
			<y23>245.375</y23>
			<x24>225.875</x24>
			<y24>245.375</y24>
			<x25>224.791667</x25>
			<y25>244.5625</y25>
			<x26>213.958333</x26>
			<y26>244.5625</y26>
			<x27>209.083333</x27>
			<y27>246.59375</y27>
			<x28>206.916667</x28>
			<y28>249.84375</y28>
			<x29>206.916667</x29>
			<y29>251.46875</y29>
			<x30>212.333333</x30>
			<y30>257.15625</y30>
			<x31>212.333333</x31>
			<y31>262.03125</y31>
			<x32>214.5</x32>
			<y32>263.65625</y32>
			<x33>216.666667</x33>
			<y33>269.34375</y33>
			<x34>218.833333</x34>
			<y34>270.96875</y34>
			<x35>222.083333</x35>
			<y35>275.84375</y35>
			<x36>223.166667</x36>
			<y36>279.90625</y36>
			<x37>226.416667</x37>
			<y37>283.96875</y37>
			<x38>236.166667</x38>
			<y38>290.46875</y38>
			<x39>240.5</x39>
			<y39>296.15625</y39>
			<x40>240.5</x40>
			<y40>297.78125</y40>
			<x41>244.291667</x41>
			<y41>301.4375</y41>
			<x42>248.625</x42>
			<y42>302.25</y42>
			<x43>251.875</x43>
			<y43>299</y43>
			<x44>254.041667</x44>
			<y44>299</y44>
			<x45>257.833333</x45>
			<y45>304.28125</y45>
			<x46>264.875</x46>
			<y46>309.5625</y46>
			<x47>278.958333</x47>
			<y47>310.375</y47>
			<x48>286.541667</x48>
			<y48>315.25</y48>
			<x49>293.041667</x49>
			<y49>316.0625</y49>
			<x50>294.125</x50>
			<y50>316.875</y50>
			<x51>310.375</x51>
			<y51>317.6875</y51>
			<x52>311.458333</x52>
			<y52>316.875</y52>
			<x53>316.875</x53>
			<y53>316.0625</y53>
			<x54>326.625</x54>
			<y54>319.3125</y54>
			<x55>332.041667</x55>
			<y55>324.1875</y55>
			<x56>339.083333</x56>
			<y56>324.59375</y56>
			<x57>339.083333</x57>
			<y57>320.53125</y57>
			<x58>336.916667</x58>
			<y58>316.46875</y58>
			<x59>328.791667</x59>
			<y59>310.375</y59>
			<x60>327.708333</x60>
			<y60>310.375</y60>
		</polygon>
	</object>
	<object>
		<name>T_L_R</name>
		<pose>Unspecified</pose>
		<truncated>0</truncated>
		<difficult>0</difficult>
		<occluded>0</occluded>
		<bndbox>
			<xmin>105</xmin>
			<xmax>210</xmax>
			<ymin>152</ymin>
			<ymax>246</ymax>
		</bndbox>
		<polygon>
			<x1>200.416667</x1>
			<y1>223.03125</y1>
			<x2>201.5</x2>
			<y2>218.96875</y2>
			<x3>202.583333</x3>
			<y3>218.15625</y3>
			<x4>201.5</x4>
			<y4>209.21875</y4>
			<x5>199.875</x5>
			<y5>206.375</y5>
			<x6>193.375</x6>
			<y6>206.375</y6>
			<x7>191.75</x7>
			<y7>205.15625</y7>
			<x8>191.75</x8>
			<y8>200.28125</y8>
			<x9>190.666667</x9>
			<y9>199.46875</y9>
			<x10>190.666667</x10>
			<y10>197.84375</y10>
			<x11>188.5</x11>
			<y11>196.21875</y11>
			<x12>188.5</x12>
			<y12>190.53125</y12>
			<x13>186.333333</x13>
			<y13>186.46875</y13>
			<x14>184.708333</x14>
			<y14>185.25</y14>
			<x15>182.541667</x15>
			<y15>185.25</y15>
			<x16>182</x16>
			<y16>187.28125</y16>
			<x17>179.291667</x17>
			<y17>189.3125</y17>
			<x18>174.958333</x18>
			<y18>191.75</y18>
			<x19>170.625</x19>
			<y19>192.5625</y19>
			<x20>166.833333</x20>
			<y20>188.90625</y20>
			<x21>165.75</x21>
			<y21>182.40625</y21>
			<x22>160.875</x22>
			<y22>177.9375</y22>
			<x23>152.208333</x23>
			<y23>173.0625</y23>
			<x24>146.791667</x24>
			<y24>173.0625</y24>
			<x25>143.541667</x25>
			<y25>171.4375</y25>
			<x26>139.208333</x26>
			<y26>167.375</y26>
			<x27>124.041667</x27>
			<y27>160.875</y27>
			<x28>109.958333</x28>
			<y28>152.75</y28>
			<x29>104.541667</x29>
			<y29>151.125</y29>
			<x30>104</x30>
			<y30>151.53125</y30>
			<x31>112.666667</x31>
			<y31>157.21875</y31>
			<x32>122.416667</x32>
			<y32>168.59375</y32>
			<x33>122.416667</x33>
			<y33>171.03125</y33>
			<x34>123.5</x34>
			<y34>171.84375</y34>
			<x35>123.5</x35>
			<y35>179.96875</y35>
			<x36>121.333333</x36>
			<y36>184.03125</y36>
			<x37>122.416667</x37>
			<y37>184.84375</y37>
			<x38>122.416667</x38>
			<y38>189.71875</y38>
			<x39>124.583333</x39>
			<y39>192.96875</y39>
			<x40>131.083333</x40>
			<y40>197.84375</y40>
			<x41>128.375</x41>
			<y41>199.0625</y41>
			<x42>125.125</x42>
			<y42>199.0625</y42>
			<x43>122.416667</x43>
			<y43>201.09375</y43>
			<x44>123.5</x44>
			<y44>201.90625</y44>
			<x45>123.5</x45>
			<y45>204.34375</y45>
			<x46>124.583333</x46>
			<y46>205.15625</y46>
			<x47>125.666667</x47>
			<y47>209.21875</y47>
			<x48>134.333333</x48>
			<y48>217.34375</y48>
			<x49>134.333333</x49>
			<y49>223.84375</y49>
			<x50>140.291667</x50>
			<y50>228.3125</y50>
			<x51>142.458333</x51>
			<y51>228.3125</y51>
			<x52>145.708333</x52>
			<y52>229.9375</y52>
			<x53>151.125</x53>
			<y53>229.9375</y53>
			<x54>153.833333</x54>
			<y54>231.15625</y54>
			<x55>152.208333</x55>
			<y55>232.375</y55>
			<x56>150.041667</x56>
			<y56>232.375</y56>
			<x57>145.708333</x57>
			<y57>234</y57>
			<x58>144.083333</x58>
			<y58>236.03125</y58>
			<x59>148.958333</x59>
			<y59>238.875</y59>
			<x60>151.125</x60>
			<y60>238.875</y60>
			<x61>152.208333</x61>
			<y61>239.6875</y61>
			<x62>158.708333</x62>
			<y62>239.6875</y62>
			<x63>167.375</x63>
			<y63>242.125</y63>
			<x64>179.291667</x64>
			<y64>242.125</y64>
			<x65>183.625</x65>
			<y65>239.6875</y65>
			<x66>186.875</x66>
			<y66>239.6875</y66>
			<x67>190.125</x67>
			<y67>241.3125</y67>
			<x68>191.208333</x68>
			<y68>242.9375</y68>
			<x69>195.541667</x69>
			<y69>244.5625</y69>
			<x70>198.25</x70>
			<y70>244.15625</y70>
			<x71>202.583333</x71>
			<y71>240.90625</y71>
			<x72>209.083333</x72>
			<y72>231.96875</y72>
			<x73>206.916667</x73>
			<y73>227.90625</y73>
			<x74>200.416667</x74>
			<y74>223.03125</y74>
		</polygon>
	</object>
	<object>
		<name>T_L_R</name>
		<pose>Unspecified</pose>
		<truncated>0</truncated>
		<difficult>0</difficult>
		<occluded>0</occluded>
		<bndbox>
			<xmin>173</xmin>
			<xmax>275</xmax>
			<ymin>121</ymin>
			<ymax>205</ymax>
		</bndbox>
		<polygon>
			<x1>271.916667</x1>
			<y1>189.71875</y1>
			<x2>269.75</x2>
			<y2>187.28125</y2>
			<x3>269.75</x3>
			<y3>182.40625</y3>
			<x4>267.583333</x4>
			<y4>178.34375</y4>
			<x5>267.583333</x5>
			<y5>174.28125</y5>
			<x6>273</x6>
			<y6>169.40625</y6>
			<x7>274.083333</x7>
			<y7>166.15625</y7>
			<x8>271.375</x8>
			<y8>164.9375</y8>
			<x9>269.208333</x9>
			<y9>165.75</y9>
			<x10>264.875</x10>
			<y10>165.75</y10>
			<x11>257.291667</x11>
			<y11>169</y11>
			<x12>255.666667</x12>
			<y12>161.28125</y12>
			<x13>252.416667</x13>
			<y13>156.40625</y13>
			<x14>248.083333</x14>
			<y14>153.96875</y14>
			<x15>248.083333</x15>
			<y15>150.71875</y15>
			<x16>243.75</x16>
			<y16>144.21875</y16>
			<x17>241.041667</x17>
			<y17>143.8125</y17>
			<x18>240.5</x18>
			<y18>145.84375</y18>
			<x19>236.708333</x19>
			<y19>148.6875</y19>
			<x20>235.083333</x20>
			<y20>147.46875</y20>
			<x21>236.166667</x21>
			<y21>146.65625</y21>
			<x22>235.083333</x22>
			<y22>140.15625</y22>
			<x23>233.458333</x23>
			<y23>138.9375</y23>
			<x24>231.291667</x24>
			<y24>138.9375</y24>
			<x25>222.625</x25>
			<y25>135.6875</y25>
			<x26>215.583333</x26>
			<y26>130.40625</y26>
			<x27>215.583333</x27>
			<y27>129.59375</y27>
			<x28>209.625</x28>
			<y28>125.9375</y28>
			<x29>191.208333</x29>
			<y29>120.25</y29>
			<x30>187.958333</x30>
			<y30>120.25</y30>
			<x31>186.875</x31>
			<y31>121.0625</y31>
			<x32>177.125</x32>
			<y32>121.0625</y32>
			<x33>174.958333</x33>
			<y33>121.875</y33>
			<x34>172.25</x34>
			<y34>123.90625</y34>
			<x35>173.875</x35>
			<y35>125.125</y35>
			<x36>176.041667</x36>
			<y36>125.125</y36>
			<x37>180.375</x37>
			<y37>126.75</y37>
			<x38>185.25</x38>
			<y38>131.21875</y38>
			<x39>185.25</x39>
			<y39>138.53125</y39>
			<x40>191.75</x40>
			<y40>145.84375</y40>
			<x41>187.416667</x41>
			<y41>150.71875</y41>
			<x42>187.416667</x42>
			<y42>152.34375</y42>
			<x43>192.833333</x43>
			<y43>159.65625</y43>
			<x44>199.333333</x44>
			<y44>164.53125</y44>
			<x45>201.5</x45>
			<y45>167.78125</y45>
			<x46>200.416667</x46>
			<y46>171.03125</y46>
			<x47>197.166667</x47>
			<y47>173.46875</y47>
			<x48>199.875</x48>
			<y48>175.5</y48>
			<x49>202.041667</x49>
			<y49>175.5</y49>
			<x50>206.916667</x50>
			<y50>177.53125</y50>
			<x51>206.916667</x51>
			<y51>179.15625</y51>
			<x52>204.75</x52>
			<y52>181.59375</y52>
			<x53>209.625</x53>
			<y53>184.4375</y53>
			<x54>217.208333</x54>
			<y54>186.0625</y54>
			<x55>219.916667</x55>
			<y55>189.71875</y55>
			<x56>228.041667</x56>
			<y56>194.1875</y56>
			<x57>232.375</x57>
			<y57>194.1875</y57>
			<x58>235.625</x58>
			<y58>196.625</y58>
			<x59>242.125</x59>
			<y59>196.625</y59>
			<x60>246.458333</x60>
			<y60>195</y60>
			<x61>257.291667</x61>
			<y61>203.9375</y61>
			<x62>258.916667</x62>
			<y62>203.53125</y62>
			<x63>262.708333</x63>
			<y63>202.3125</y63>
			<x64>266.5</x64>
			<y64>199.46875</y64>
			<x65>270.833333</x65>
			<y65>193.78125</y65>
			<x66>271.916667</x66>
			<y66>189.71875</y66>
		</polygon>
	</object>
	<object>
		<name>T_L_R</name>
		<pose>Unspecified</pose>
		<truncated>0</truncated>
		<difficult>0</difficult>
		<occluded>0</occluded>
		<bndbox>
			<xmin>270</xmin>
			<xmax>387</xmax>
			<ymin>203</ymin>
			<ymax>291</ymax>
		</bndbox>
		<polygon>
			<x1>384.583333</x1>
			<y1>275.03125</y1>
			<x2>380.25</x2>
			<y2>267.71875</y2>
			<x3>378.083333</x3>
			<y3>266.09375</y3>
			<x4>373.75</x4>
			<y4>259.59375</y4>
			<x5>373.75</x5>
			<y5>257.96875</y5>
			<x6>366.166667</x6>
			<y6>252.28125</y6>
			<x7>366.166667</x7>
			<y7>250.65625</y7>
			<x8>362.916667</x8>
			<y8>246.59375</y8>
			<x9>351.541667</x9>
			<y9>237.25</y9>
			<x10>347.208333</x10>
			<y10>235.625</y10>
			<x11>343.958333</x11>
			<y11>233.1875</y11>
			<x12>339.625</x12>
			<y12>231.5625</y12>
			<x13>337.458333</x13>
			<y13>231.5625</y13>
			<x14>326.625</x14>
			<y14>226.6875</y14>
			<x15>321.208333</x15>
			<y15>226.6875</y15>
			<x16>317.416667</x16>
			<y16>223.84375</y16>
			<x17>318.5</x17>
			<y17>219.78125</y17>
			<x18>315.791667</x18>
			<y18>217.75</y18>
			<x19>303.333333</x19>
			<y19>214.90625</y19>
			<x20>303.333333</x20>
			<y20>213.28125</y20>
			<x21>306.041667</x21>
			<y21>211.25</y21>
			<x22>309.291667</x22>
			<y22>210.4375</y22>
			<x23>314.166667</x23>
			<y23>206.78125</y23>
			<x24>316.333333</x24>
			<y24>204.34375</y24>
			<x25>315.791667</x25>
			<y25>203.125</y25>
			<x26>309.291667</x26>
			<y26>202.3125</y26>
			<x27>308.208333</x27>
			<y27>203.125</y27>
			<x28>302.791667</x28>
			<y28>203.125</y28>
			<x29>301.708333</x29>
			<y29>203.9375</y29>
			<x30>291.958333</x30>
			<y30>203.9375</y30>
			<x31>283.291667</x31>
			<y31>206.375</y31>
			<x32>278.958333</x32>
			<y32>206.375</y32>
			<x33>273</x33>
			<y33>208.40625</y33>
			<x34>270.833333</x34>
			<y34>214.09375</y34>
			<x35>274.083333</x35>
			<y35>218.96875</y35>
			<x36>271.375</x36>
			<y36>220.1875</y36>
			<x37>268.666667</x37>
			<y37>223.03125</y37>
			<x38>268.666667</x38>
			<y38>228.71875</y38>
			<x39>273</x39>
			<y39>231.96875</y39>
			<x40>277.333333</x40>
			<y40>239.28125</y40>
			<x41>280.583333</x41>
			<y41>241.71875</y41>
			<x42>281.666667</x42>
			<y42>247.40625</y42>
			<x43>286.541667</x43>
			<y43>251.875</y43>
			<x44>289.25</x44>
			<y44>250.65625</y44>
			<x45>290.333333</x45>
			<y45>247.40625</y45>
			<x46>291.958333</x46>
			<y46>247</y46>
			<x47>293.583333</x47>
			<y47>248.21875</y47>
			<x48>293.583333</x48>
			<y48>249.84375</y48>
			<x49>295.75</x49>
			<y49>253.09375</y49>
			<x50>312.541667</x50>
			<y50>264.875</y50>
			<x51>316.875</x51>
			<y51>264.0625</y51>
			<x52>318.5</x52>
			<y52>267.71875</y52>
			<x53>321.208333</x53>
			<y53>269.75</y53>
			<x54>326.625</x54>
			<y54>268.9375</y54>
			<x55>336.375</x55>
			<y55>272.1875</y55>
			<x56>345.041667</x56>
			<y56>273</y56>
			<x57>358.041667</x57>
			<y57>277.875</y57>
			<x58>364</x58>
			<y58>282.34375</y58>
			<x59>364</x59>
			<y59>283.15625</y59>
			<x60>367.791667</x60>
			<y60>285.1875</y60>
			<x61>372.125</x61>
			<y61>286.8125</y61>
			<x62>374.291667</x62>
			<y62>286.8125</y62>
			<x63>378.625</x63>
			<y63>289.25</y63>
			<x64>380.791667</x64>
			<y64>289.25</y64>
			<x65>381.875</x65>
			<y65>290.0625</y65>
			<x66>383.5</x66>
			<y66>289.65625</y66>
			<x67>384.583333</x67>
			<y67>288.84375</y67>
			<x68>384.583333</x68>
			<y68>284.78125</y68>
			<x69>385.666667</x69>
			<y69>283.96875</y69>
			<x70>384.583333</x70>
			<y70>275.03125</y70>
		</polygon>
	</object>
	<object>
		<name>T_L_R</name>
		<pose>Unspecified</pose>
		<truncated>0</truncated>
		<difficult>0</difficult>
		<occluded>0</occluded>
		<bndbox>
			<xmin>271</xmin>
			<xmax>336</xmax>
			<ymin>81</ymin>
			<ymax>170</ymax>
		</bndbox>
		<polygon>
			<x1>319.041667</x1>
			<y1>160.0625</y1>
			<x2>327.708333</x2>
			<y2>152.75</y2>
			<x3>332.041667</x3>
			<y3>151.125</y3>
			<x4>334.75</x4>
			<y4>148.28125</y4>
			<x5>334.75</x5>
			<y5>146.65625</y5>
			<x6>332.041667</x6>
			<y6>145.4375</y6>
			<x7>330.958333</x7>
			<y7>146.25</y7>
			<x8>319.583333</x8>
			<y8>146.65625</y8>
			<x9>320.666667</x9>
			<y9>141.78125</y9>
			<x10>321.75</x10>
			<y10>140.96875</y10>
			<x11>321.75</x11>
			<y11>132.84375</y11>
			<x12>320.666667</x12>
			<y12>132.03125</y12>
			<x13>320.666667</x13>
			<y13>127.15625</y13>
			<x14>321.75</x14>
			<y14>125.53125</y14>
			<x15>319.041667</x15>
			<y15>123.5</y15>
			<x16>316.333333</x16>
			<y16>123.09375</y16>
			<x17>317.416667</x17>
			<y17>115.78125</y17>
			<x18>315.791667</x18>
			<y18>114.5625</y18>
			<x19>313.083333</x19>
			<y19>114.15625</y19>
			<x20>313.083333</x20>
			<y20>109.28125</y20>
			<x21>309.833333</x21>
			<y21>106.03125</y21>
			<x22>307.666667</x22>
			<y22>100.34375</y22>
			<x23>293.041667</x23>
			<y23>88.5625</y23>
			<x24>288.708333</x24>
			<y24>87.75</y24>
			<x25>286.541667</x25>
			<y25>86.125</y25>
			<x26>280.041667</x26>
			<y26>83.6875</y26>
			<x27>277.875</x27>
			<y27>83.6875</y27>
			<x28>275.708333</x28>
			<y28>82.0625</y28>
			<x29>270.291667</x29>
			<y29>80.4375</y29>
			<x30>269.75</x30>
			<y30>82.46875</y30>
			<x31>271.916667</x31>
			<y31>84.09375</y31>
			<x32>273</x32>
			<y32>88.15625</y32>
			<x33>274.083333</x33>
			<y33>88.96875</y33>
			<x34>274.083333</x34>
			<y34>109.28125</y34>
			<x35>275.166667</x35>
			<y35>110.09375</y35>
			<x36>275.166667</x36>
			<y36>113.34375</y36>
			<x37>277.333333</x37>
			<y37>115.78125</y37>
			<x38>277.333333</x38>
			<y38>118.21875</y38>
			<x39>275.166667</x39>
			<y39>121.46875</y39>
			<x40>275.166667</x40>
			<y40>127.15625</y40>
			<x41>277.333333</x41>
			<y41>129.59375</y41>
			<x42>278.416667</x42>
			<y42>132.84375</y42>
			<x43>281.666667</x43>
			<y43>136.09375</y43>
			<x44>278.958333</x44>
			<y44>137.3125</y44>
			<x45>277.333333</x45>
			<y45>139.34375</y45>
			<x46>284.916667</x46>
			<y46>144.21875</y46>
			<x47>284.916667</x47>
			<y47>147.46875</y47>
			<x48>291.958333</x48>
			<y48>152.75</y48>
			<x49>294.125</x49>
			<y49>152.75</y49>
			<x50>295.75</x50>
			<y50>153.96875</y50>
			<x51>294.666667</x51>
			<y51>154.78125</y51>
			<x52>294.666667</x52>
			<y52>157.21875</y52>
			<x53>302.791667</x53>
			<y53>158.4375</y53>
			<x54>307.125</x54>
			<y54>160.0625</y54>
			<x55>314.166667</x55>
			<y55>166.96875</y55>
			<x56>314.166667</x56>
			<y56>168.59375</y56>
			<x57>316.333333</x57>
			<y57>168.59375</y57>
			<x58>313.083333</x58>
			<y58>163.71875</y58>
			<x59>313.083333</x59>
			<y59>162.09375</y59>
			<x60>316.875</x60>
			<y60>160.0625</y60>
			<x61>319.041667</x61>
			<y61>160.0625</y61>
		</polygon>
	</object>
	<object>
		<name>T_L_R</name>
		<pose>Unspecified</pose>
		<truncated>0</truncated>
		<difficult>0</difficult>
		<occluded>0</occluded>
		<bndbox>
			<xmin>329</xmin>
			<xmax>416</xmax>
			<ymin>154</ymin>
			<ymax>189</ymax>
		</bndbox>
		<polygon>
			<x1>388.375</x1>
			<y1>184.4375</y1>
			<x2>392.708333</x2>
			<y2>182.8125</y2>
			<x3>395.958333</x3>
			<y3>182.8125</y3>
			<x4>412.208333</x4>
			<y4>177.125</y4>
			<x5>414.916667</x5>
			<y5>175.09375</y5>
			<x6>414.916667</x6>
			<y6>156.40625</y6>
			<x7>411.125</x7>
			<y7>156</y7>
			<x8>410.041667</x8>
			<y8>155.1875</y8>
			<x9>405.708333</x9>
			<y9>155.1875</y9>
			<x10>400.291667</x10>
			<y10>156.8125</y10>
			<x11>395.958333</x11>
			<y11>156.8125</y11>
			<x12>389.458333</x12>
			<y12>159.25</y12>
			<x13>385.125</x13>
			<y13>159.25</y13>
			<x14>382.416667</x14>
			<y14>157.21875</y14>
			<x15>383.5</x15>
			<y15>155.59375</y15>
			<x16>379.708333</x16>
			<y16>153.5625</y16>
			<x17>367.791667</x17>
			<y17>156.8125</y17>
			<x18>364.541667</x18>
			<y18>156.8125</y18>
			<x19>361.291667</x19>
			<y19>152.75</y19>
			<x20>358.041667</x20>
			<y20>152.75</y20>
			<x21>354.791667</x21>
			<y21>155.1875</y21>
			<x22>347.208333</x22>
			<y22>156</y22>
			<x23>342.875</x23>
			<y23>158.4375</y23>
			<x24>342.333333</x24>
			<y24>157.21875</y24>
			<x25>339.625</x25>
			<y25>156</y25>
			<x26>334.208333</x26>
			<y26>161.6875</y26>
			<x27>330.958333</x27>
			<y27>161.6875</y27>
			<x28>329.333333</x28>
			<y28>162.90625</y28>
			<x29>328.25</x29>
			<y29>167.78125</y29>
			<x30>331.5</x30>
			<y30>172.65625</y30>
			<x31>334.75</x31>
			<y31>175.09375</y31>
			<x32>334.75</x32>
			<y32>180.78125</y32>
			<x33>337.458333</x33>
			<y33>182.8125</y33>
			<x34>339.625</x34>
			<y34>182.8125</y34>
			<x35>342.875</x35>
			<y35>184.4375</y35>
			<x36>346.125</x36>
			<y36>184.4375</y36>
			<x37>347.208333</x37>
			<y37>185.25</y37>
			<x38>352.625</x38>
			<y38>185.25</y38>
			<x39>353.708333</x39>
			<y39>186.0625</y39>
			<x40>359.125</x40>
			<y40>185.25</y40>
			<x41>363.458333</x41>
			<y41>187.6875</y41>
			<x42>367.25</x42>
			<y42>187.28125</y42>
			<x43>369.958333</x43>
			<y43>185.25</y43>
			<x44>376.458333</x44>
			<y44>185.25</y44>
			<x45>378.625</x45>
			<y45>183.625</y45>
			<x46>388.375</x46>
			<y46>184.4375</y46>
		</polygon>
	</object>
	<object>
		<name>T_S_R</name>
		<pose>Unspecified</pose>
		<truncated>0</truncated>
		<difficult>0</difficult>
		<occluded>0</occluded>
		<bndbox>
			<xmin>183</xmin>
			<xmax>333</xmax>
			<ymin>170</ymin>
			<ymax>261</ymax>
		</bndbox>
		<polygon>
			<x1>202.041667</x1>
			<y1>250.25</y1>
			<x2>205.291667</x2>
			<y2>249.4375</y2>
			<x3>205.833333</x3>
			<y3>248.21875</y3>
			<x4>226.416667</x4>
			<y4>233.59375</y4>
			<x5>228.583333</x5>
			<y5>231.15625</y5>
			<x6>228.583333</x6>
			<y6>228.71875</y6>
			<x7>231.291667</x7>
			<y7>226.6875</y7>
			<x8>235.625</x8>
			<y8>226.6875</y8>
			<x9>239.958333</x9>
			<y9>224.25</y9>
			<x10>242.125</x10>
			<y10>221.8125</y10>
			<x11>247.541667</x11>
			<y11>220.1875</y11>
			<x12>254.041667</x12>
			<y12>215.3125</y12>
			<x13>262.708333</x13>
			<y13>210.4375</y13>
			<x14>269.208333</x14>
			<y14>212.875</y14>
			<x15>269.75</x15>
			<y15>210.84375</y15>
			<x16>268.666667</x16>
			<y16>210.03125</y16>
			<x17>268.666667</x17>
			<y17>208.40625</y17>
			<x18>293.041667</x18>
			<y18>191.75</y18>
			<x19>301.708333</x19>
			<y19>187.6875</y19>
			<x20>304.958333</x20>
			<y20>182.8125</y20>
			<x21>307.125</x21>
			<y21>182</y21>
			<x22>311.458333</x22>
			<y22>182</y22>
			<x23>323.375</x23>
			<y23>176.3125</y23>
			<x24>328.791667</x24>
			<y24>176.3125</y24>
			<x25>330.958333</x25>
			<y25>175.5</y25>
			<x26>331.5</x26>
			<y26>173.46875</y26>
			<x27>329.333333</x27>
			<y27>170.21875</y27>
			<x28>327.708333</x28>
			<y28>169</y28>
			<x29>325.541667</x29>
			<y29>169</y29>
			<x30>322.291667</x30>
			<y30>170.625</y30>
			<x31>317.958333</x31>
			<y31>171.4375</y31>
			<x32>313.625</x32>
			<y32>174.6875</y32>
			<x33>306.041667</x33>
			<y33>177.9375</y33>
			<x34>300.625</x34>
			<y34>182</y34>
			<x35>286.541667</x35>
			<y35>188.5</y35>
			<x36>283.291667</x36>
			<y36>190.9375</y36>
			<x37>270.291667</x37>
			<y37>197.4375</y37>
			<x38>263.791667</x38>
			<y38>202.3125</y38>
			<x39>259.458333</x39>
			<y39>203.9375</y39>
			<x40>252.958333</x40>
			<y40>209.625</y40>
			<x41>235.625</x41>
			<y41>219.375</y41>
			<x42>232.916667</x42>
			<y42>222.21875</y42>
			<x43>229.125</x43>
			<y43>224.25</y43>
			<x44>226.958333</x44>
			<y44>226.6875</y44>
			<x45>223.708333</x45>
			<y45>227.5</y45>
			<x46>223.166667</x46>
			<y46>228.71875</y46>
			<x47>221.541667</x47>
			<y47>229.125</y47>
			<x48>210.166667</x48>
			<y48>237.65625</y48>
			<x49>209.625</x49>
			<y49>238.875</y49>
			<x50>203.125</x50>
			<y50>242.125</y50>
			<x51>197.166667</x51>
			<y51>246.59375</y51>
			<x52>197.166667</x52>
			<y52>247.40625</y52>
			<x53>182</x53>
			<y53>257.96875</y53>
			<x54>182</x54>
			<y54>259.59375</y54>
			<x55>184.166667</x55>
			<y55>259.59375</y55>
			<x56>187.958333</x56>
			<y56>259.1875</y56>
			<x57>194.458333</x57>
			<y57>254.3125</y57>
			<x58>198.791667</x58>
			<y58>252.6875</y58>
			<x59>202.041667</x59>
			<y59>250.25</y59>
		</polygon>
	</object>
</annotation>
