<annotation>
	<folder></folder>
	<filename>00072_jpg.rf.476b4f980d092bb3049c29cf50096403.jpg</filename>
	<path>00072_jpg.rf.476b4f980d092bb3049c29cf50096403.jpg</path>
	<source>
		<database>roboflow.com</database>
	</source>
	<size>
		<width>1280</width>
		<height>1280</height>
		<depth>3</depth>
	</size>
	<segmented>0</segmented>
	<object>
		<name>T_F_R</name>
		<pose>Unspecified</pose>
		<truncated>0</truncated>
		<difficult>0</difficult>
		<occluded>0</occluded>
		<bndbox>
			<xmin>439</xmin>
			<xmax>864</xmax>
			<ymin>347</ymin>
			<ymax>933</ymax>
		</bndbox>
		<polygon>
			<x1>862.4</x1>
			<y1>708.8</y1>
			<x2>851.2</x2>
			<y2>628.8</y2>
			<x3>844</x3>
			<y3>598.933333</y3>
			<x4>832</x4>
			<y4>558.4</y4>
			<x5>814.4</x5>
			<y5>518.933333</y5>
			<x6>781.6</x6>
			<y6>459.2</y6>
			<x7>748.4</x7>
			<y7>422.4</y7>
			<x8>662</x8>
			<y8>374.4</y8>
			<x9>598</x9>
			<y9>349.866667</y9>
			<x10>566</x10>
			<y10>345.6</y10>
			<x11>542</x11>
			<y11>350.933333</y11>
			<x12>526</x12>
			<y12>360.533333</y12>
			<x13>500.8</x13>
			<y13>387.733333</y13>
			<x14>458.4</x14>
			<y14>456</y14>
			<x15>446.4</x15>
			<y15>486.933333</y15>
			<x16>437.6</x16>
			<y16>576.533333</y16>
			<x17>437.6</x17>
			<y17>657.6</y17>
			<x18>440.8</x18>
			<y18>696</y18>
			<x19>448</x19>
			<y19>730.133333</y19>
			<x20>477.6</x20>
			<y20>810.133333</y20>
			<x21>506</x21>
			<y21>854.4</y21>
			<x22>537.2</x22>
			<y22>887.466667</y22>
			<x23>570.8</x23>
			<y23>907.733333</y23>
			<x24>630.8</x24>
			<y24>928</y24>
			<x25>692</x25>
			<y25>931.733333</y25>
			<x26>786.8</x26>
			<y26>921.6</y26>
			<x27>820.4</x27>
			<y27>899.2</y27>
			<x28>843.2</x28>
			<y28>865.6</y28>
			<x29>856.8</x29>
			<y29>826.133333</y29>
			<x30>863.2</x30>
			<y30>769.6</y30>
			<x31>862.4</x31>
			<y31>708.8</y31>
		</polygon>
	</object>
	<object>
		<name>T_F_R</name>
		<pose>Unspecified</pose>
		<truncated>0</truncated>
		<difficult>0</difficult>
		<occluded>0</occluded>
		<bndbox>
			<xmin>954</xmin>
			<xmax>1281</xmax>
			<ymin>191</ymin>
			<ymax>601</ymax>
		</bndbox>
		<polygon>
			<x1>1280</x1>
			<y1>225</y1>
			<x2>1261.25</x2>
			<y2>210</y2>
			<x3>1233.75</x3>
			<y3>196.666667</y3>
			<x4>1208.75</x4>
			<y4>193.333333</y4>
			<x5>1206.25</x5>
			<y5>190</y5>
			<x6>1166.25</x6>
			<y6>190</y6>
			<x7>1148.75</x7>
			<y7>196.666667</y7>
			<x8>1131.25</x8>
			<y8>196.666667</y8>
			<x9>1123.75</x9>
			<y9>203.333333</y9>
			<x10>1116.25</x10>
			<y10>203.333333</y10>
			<x11>1093.75</x11>
			<y11>216.666667</y11>
			<x12>1078.75</x12>
			<y12>220</y12>
			<x13>1051.25</x13>
			<y13>236.666667</y13>
			<x14>1033.75</x14>
			<y14>253.333333</y14>
			<x15>980</x15>
			<y15>328.333333</y15>
			<x16>962.5</x16>
			<y16>368.333333</y16>
			<x17>957.5</x17>
			<y17>385</y17>
			<x18>957.5</x18>
			<y18>415</y18>
			<x19>952.5</x19>
			<y19>425</y19>
			<x20>952.5</x20>
			<y20>441.666667</y20>
			<x21>965</x21>
			<y21>458.333333</y21>
			<x22>965</x22>
			<y22>468.333333</y22>
			<x23>970</x23>
			<y23>481.666667</y23>
			<x24>986.25</x24>
			<y24>506.666667</y24>
			<x25>1013.75</x25>
			<y25>533.333333</y25>
			<x26>1063.75</x26>
			<y26>560</y26>
			<x27>1086.25</x27>
			<y27>576.666667</y27>
			<x28>1093.75</x28>
			<y28>576.666667</y28>
			<x29>1108.75</x29>
			<y29>586.666667</y29>
			<x30>1146.25</x30>
			<y30>596.666667</y30>
			<x31>1161.25</x31>
			<y31>596.666667</y31>
			<x32>1163.75</x32>
			<y32>600</y32>
			<x33>1210</x33>
			<y33>598.333333</y33>
			<x34>1251.25</x34>
			<y34>590</y34>
			<x35>1280</x35>
			<y35>571.666667</y35>
			<x36>1280</x36>
			<y36>225</y36>
		</polygon>
	</object>
</annotation>
