<annotation>
	<folder></folder>
	<filename>00125_jpg.rf.8154ea47d65a3dceed7963fca20d9856.jpg</filename>
	<path>00125_jpg.rf.8154ea47d65a3dceed7963fca20d9856.jpg</path>
	<source>
		<database>roboflow.com</database>
	</source>
	<size>
		<width>1280</width>
		<height>1280</height>
		<depth>3</depth>
	</size>
	<segmented>0</segmented>
	<object>
		<name>T_F_R</name>
		<pose>Unspecified</pose>
		<truncated>0</truncated>
		<difficult>0</difficult>
		<occluded>0</occluded>
		<bndbox>
			<xmin>456</xmin>
			<xmax>612</xmax>
			<ymin>67</ymin>
			<ymax>302</ymax>
		</bndbox>
		<polygon>
			<x1>454.846512</x1>
			<y1>150.825457</y1>
			<x2>456.632558</x2>
			<y2>182.281033</y2>
			<x3>463.776744</x3>
			<y3>212.123503</y3>
			<x4>475.088372</x4>
			<y4>237.126654</y4>
			<x5>488.186047</x5>
			<y5>255.677379</y5>
			<x6>509.023256</x6>
			<y6>276.647763</y6>
			<x7>526.883721</x7>
			<y7>290.359168</y7>
			<x8>547.72093</x8>
			<y8>300.84436</y8>
			<x9>578.083721</x9>
			<y9>299.231254</y9>
			<x10>588.204651</x10>
			<y10>293.585381</y10>
			<x11>595.944186</x11>
			<y11>284.713296</y11>
			<x12>610.232558</x12>
			<y12>249.224953</y12>
			<x13>611.423256</x13>
			<y13>220.189036</y13>
			<x14>607.851163</x14>
			<y14>186.3138</y14>
			<x15>599.516279</x15>
			<y15>157.277883</y15>
			<x16>598.325581</x16>
			<y16>138.727158</y16>
			<x17>571.534884</x17>
			<y17>93.560176</y17>
			<x18>552.483721</x18>
			<y18>78.235665</y18>
			<x19>527.47907</x19>
			<y19>66.137366</y19>
			<x20>490.567442</x20>
			<y20>87.914304</y20>
			<x21>461.395349</x21>
			<y21>129.855072</y21>
			<x22>454.846512</x22>
			<y22>150.825457</y22>
		</polygon>
	</object>
	<object>
		<name>T_F_R</name>
		<pose>Unspecified</pose>
		<truncated>0</truncated>
		<difficult>0</difficult>
		<occluded>0</occluded>
		<bndbox>
			<xmin>316</xmin>
			<xmax>432</xmax>
			<ymin>320</ymin>
			<ymax>507</ymax>
		</bndbox>
		<polygon>
			<x1>322.083721</x1>
			<y1>362.94896</y1>
			<x2>316.130233</x2>
			<y2>388.758664</y2>
			<x3>314.939535</x3>
			<y3>424.247007</y3>
			<x4>316.725581</x4>
			<y4>439.571519</y4>
			<x5>328.037209</x5>
			<y5>483.931947</y5>
			<x6>339.944186</x6>
			<y6>505.708885</y6>
			<x7>348.27907</x7>
			<y7>495.223693</y7>
			<x8>365.544186</x8>
			<y8>492.804033</y8>
			<x9>375.069767</x9>
			<y9>483.125394</y9>
			<x10>398.288372</x10>
			<y10>483.931947</y10>
			<x11>418.530233</x11>
			<y11>489.57782</y11>
			<x12>421.506977</x12>
			<y12>483.931947</y12>
			<x13>423.293023</x13>
			<y13>461.348456</y13>
			<x14>431.032558</x14>
			<y14>446.830498</y14>
			<x15>428.651163</x15>
			<y15>373.434152</y15>
			<x16>423.888372</x16>
			<y16>362.94896</y16>
			<x17>421.506977</x17>
			<y17>348.431002</y17>
			<x18>411.981395</x18>
			<y18>336.332703</y18>
			<x19>394.716279</x19>
			<y19>322.621298</y19>
			<x20>365.544186</x20>
			<y20>319.395085</y20>
			<x21>353.637209</x21>
			<y21>322.621298</y21>
			<x22>332.204651</x22>
			<y22>337.94581</y22>
			<x23>322.083721</x23>
			<y23>362.94896</y23>
		</polygon>
	</object>
	<object>
		<name>T_F_R</name>
		<pose>Unspecified</pose>
		<truncated>0</truncated>
		<difficult>0</difficult>
		<occluded>0</occluded>
		<bndbox>
			<xmin>440</xmin>
			<xmax>555</xmax>
			<ymin>283</ymin>
			<ymax>452</ymax>
		</bndbox>
		<polygon>
			<x1>439.367442</x1>
			<y1>332.299937</y1>
			<x2>441.748837</x2>
			<y2>368.594833</y2>
			<x3>447.106977</x3>
			<y3>397.63075</y3>
			<x4>456.632558</x4>
			<y4>425.05356</y4>
			<x5>469.730233</x5>
			<y5>450.863264</y5>
			<x6>473.897674</x6>
			<y6>449.250158</y6>
			<x7>483.423256</x7>
			<y7>437.151859</y7>
			<x8>493.544186</x8>
			<y8>415.374921</y8>
			<x9>520.930233</x9>
			<y9>391.178324</y9>
			<x10>550.697674</x10>
			<y10>375.047259</y10>
			<x11>553.674419</x11>
			<y11>367.78828</y11>
			<x12>552.483721</x12>
			<y12>354.076875</y12>
			<x13>545.934884</x13>
			<y13>336.332703</y13>
			<x14>538.195349</x14>
			<y14>326.654064</y14>
			<x15>534.027907</x15>
			<y15>312.136106</y15>
			<x16>513.190698</x16>
			<y16>286.326402</y16>
			<x17>507.237209</x17>
			<y17>282.293636</y17>
			<x18>497.711628</x18>
			<y18>282.293636</y18>
			<x19>451.869767</x19>
			<y19>304.070573</y19>
			<x20>444.130233</x20>
			<y20>314.555766</y20>
			<x21>439.367442</x21>
			<y21>332.299937</y21>
		</polygon>
	</object>
	<object>
		<name>T_L_R</name>
		<pose>Unspecified</pose>
		<truncated>0</truncated>
		<difficult>0</difficult>
		<occluded>0</occluded>
		<bndbox>
			<xmin>264</xmin>
			<xmax>464</xmax>
			<ymin>750</ymin>
			<ymax>1220</ymax>
		</bndbox>
		<polygon>
			<x1>327.5</x1>
			<y1>814.547889</y1>
			<x2>332.5</x2>
			<y2>824.70857</y2>
			<x3>332.5</x3>
			<y3>831.482357</y3>
			<x4>313.75</x4>
			<y4>846.723378</y4>
			<x5>307.5</x5>
			<y5>855.190611</y5>
			<x6>305</x6>
			<y6>865.351292</y6>
			<x7>267.5</x7>
			<y7>912.767801</y7>
			<x8>262.5</x8>
			<y8>926.315375</y8>
			<x9>262.5</x9>
			<y9>939.862949</y9>
			<x10>273.75</x10>
			<y10>951.717076</y10>
			<x11>291.25</x11>
			<y11>948.330183</y11>
			<x12>301.25</x12>
			<y12>934.782609</y12>
			<x13>311.25</x13>
			<y13>934.782609</y13>
			<x14>315</x14>
			<y14>939.862949</y14>
			<x15>315</x15>
			<y15>946.636736</y15>
			<x16>307.5</x16>
			<y16>963.571203</y16>
			<x17>307.5</x17>
			<y17>980.505671</y17>
			<x18>305</x18>
			<y18>983.892565</y18>
			<x19>302.5</x19>
			<y19>1017.761499</y19>
			<x20>300</x20>
			<y20>1021.148393</y20>
			<x21>300</x21>
			<y21>1041.469755</y21>
			<x22>297.5</x22>
			<y22>1044.856647</y22>
			<x23>297.5</x23>
			<y23>1068.564903</y23>
			<x24>300</x24>
			<y24>1071.951796</y24>
			<x25>302.5</x25>
			<y25>1095.660051</y25>
			<x26>305</x26>
			<y26>1099.046944</y26>
			<x27>305</x27>
			<y27>1136.302773</y27>
			<x28>310</x28>
			<y28>1146.463453</y28>
			<x29>310</x29>
			<y29>1153.23724</y29>
			<x30>315</x30>
			<y30>1166.784814</y30>
			<x31>332.5</x31>
			<y31>1190.493069</y31>
			<x32>337.5</x32>
			<y32>1204.040643</y32>
			<x33>337.5</x33>
			<y33>1214.201323</y33>
			<x34>341.25</x34>
			<y34>1219.281664</y34>
			<x35>345</x35>
			<y35>1210.81443</y35>
			<x36>345</x36>
			<y36>1187.106175</y36>
			<x37>347.5</x37>
			<y37>1183.719282</y37>
			<x38>347.5</x38>
			<y38>1173.558601</y38>
			<x39>345</x39>
			<y39>1170.171708</y39>
			<x40>348.75</x40>
			<y40>1161.704474</y40>
			<x41>358.75</x41>
			<y41>1161.704474</y41>
			<x42>362.5</x42>
			<y42>1156.624133</y42>
			<x43>365</x43>
			<y43>1149.850347</y43>
			<x44>365</x44>
			<y44>1139.689666</y44>
			<x45>362.5</x45>
			<y45>1136.302773</y45>
			<x46>365</x46>
			<y46>1115.981411</y46>
			<x47>370</x47>
			<y47>1109.207625</y47>
			<x48>377.5</x48>
			<y48>1088.886263</y48>
			<x49>377.5</x49>
			<y49>1082.112477</y49>
			<x50>390</x50>
			<y50>1058.404221</y50>
			<x51>390</x51>
			<y51>1048.243541</y51>
			<x52>395</x52>
			<y52>1031.309073</y52>
			<x53>395</x53>
			<y53>1004.213925</y53>
			<x54>400</x54>
			<y54>1004.213925</y54>
			<x55>402.5</x55>
			<y55>1007.600819</y55>
			<x56>410</x56>
			<y56>1031.309073</y56>
			<x57>416.25</x57>
			<y57>1039.776307</y57>
			<x58>433.75</x58>
			<y58>1049.936988</y58>
			<x59>446.25</x59>
			<y59>1049.936988</y59>
			<x60>448.75</x60>
			<y60>1053.323881</y60>
			<x61>453.75</x61>
			<y61>1053.323881</y61>
			<x62>460</x62>
			<y62>1048.243541</y62>
			<x63>460</x63>
			<y63>1041.469755</y63>
			<x64>462.5</x64>
			<y64>1038.082861</y64>
			<x65>462.5</x65>
			<y65>1021.148393</y65>
			<x66>455</x66>
			<y66>1000.827032</y66>
			<x67>455</x67>
			<y67>987.279458</y67>
			<x68>452.5</x68>
			<y68>983.892565</y68>
			<x69>452.5</x69>
			<y69>963.571203</y69>
			<x70>455</x70>
			<y70>960.18431</y70>
			<x71>455</x71>
			<y71>855.190611</y71>
			<x72>452.5</x72>
			<y72>851.803718</y72>
			<x73>450</x73>
			<y73>834.86925</y73>
			<x74>427.5</x74>
			<y74>797.613422</y74>
			<x75>425</x75>
			<y75>787.452741</y75>
			<x76>415</x76>
			<y76>770.518274</y76>
			<x77>415</x77>
			<y77>763.744486</y77>
			<x78>403.75</x78>
			<y78>751.890359</y78>
			<x79>381.25</x79>
			<y79>751.890359</y79>
			<x80>378.75</x80>
			<y80>748.503466</y80>
			<x81>358.75</x81>
			<y81>748.503466</y81>
			<x82>356.25</x82>
			<y82>751.890359</y82>
			<x83>348.75</x83>
			<y83>751.890359</y83>
			<x84>331.25</x84>
			<y84>768.824827</y84>
			<x85>321.25</x85>
			<y85>775.598614</y85>
			<x86>316.25</x86>
			<y86>775.598614</y86>
			<x87>315</x87>
			<y87>777.29206</y87>
			<x88>317.5</x88>
			<y88>780.678954</y88>
			<x89>312.5</x89>
			<y89>784.065848</y89>
			<x90>312.5</x90>
			<y90>794.226528</y90>
			<x91>320</x91>
			<y91>804.387208</y91>
			<x92>320</x92>
			<y92>807.774102</y92>
			<x93>327.5</x93>
			<y93>814.547889</y93>
		</polygon>
	</object>
	<object>
		<name>T_L_R</name>
		<pose>Unspecified</pose>
		<truncated>0</truncated>
		<difficult>0</difficult>
		<occluded>0</occluded>
		<bndbox>
			<xmin>426</xmin>
			<xmax>634</xmax>
			<ymin>915</ymin>
			<ymax>1261</ymax>
		</bndbox>
		<polygon>
			<x1>428.75</x1>
			<y1>1259.924386</y1>
			<x2>436.25</x2>
			<y2>1249.763705</y2>
			<x3>451.25</x3>
			<y3>1239.603024</y3>
			<x4>463.75</x4>
			<y4>1239.603024</y4>
			<x5>473.75</x5>
			<y5>1229.442344</y5>
			<x6>483.75</x6>
			<y6>1229.442344</y6>
			<x7>496.25</x7>
			<y7>1219.281664</y7>
			<x8>511.25</x8>
			<y8>1215.89477</y8>
			<x9>513.75</x9>
			<y9>1212.507876</y9>
			<x10>516.25</x10>
			<y10>1215.89477</y10>
			<x11>536.25</x11>
			<y11>1202.347196</y11>
			<x12>558.75</x12>
			<y12>1168.478261</y12>
			<x13>563.75</x13>
			<y13>1168.478261</y13>
			<x14>581.25</x14>
			<y14>1192.186515</y14>
			<x15>586.25</x15>
			<y15>1192.186515</y15>
			<x16>590</x16>
			<y16>1180.332388</y16>
			<x17>590</x17>
			<y17>1143.076559</y17>
			<x18>608.75</x18>
			<y18>1107.514177</y18>
			<x19>611.25</x19>
			<y19>1110.901071</y19>
			<x20>616.25</x20>
			<y20>1110.901071</y20>
			<x21>620</x21>
			<y21>1105.820731</y21>
			<x22>620</x22>
			<y22>1088.886263</y22>
			<x23>617.5</x23>
			<y23>1085.49937</y23>
			<x24>617.5</x24>
			<y24>1055.017329</y24>
			<x25>632.5</x25>
			<y25>1055.017329</y25>
			<x26>630</x26>
			<y26>1017.761499</y26>
			<x27>611.25</x27>
			<y27>999.133585</y27>
			<x28>607.5</x28>
			<y28>990.666351</y28>
			<x29>627.5</x29>
			<y29>950.023629</y29>
			<x30>603.75</x30>
			<y30>921.235035</y30>
			<x31>593.75</x31>
			<y31>914.461247</y31>
			<x32>578.75</x32>
			<y32>914.461247</y32>
			<x33>561.25</x33>
			<y33>924.621928</y33>
			<x34>538.75</x34>
			<y34>921.235035</y34>
			<x35>532.5</x35>
			<y35>929.702269</y35>
			<x36>532.5</x36>
			<y36>946.636736</y36>
			<x37>535</x37>
			<y37>953.410523</y37>
			<x38>528.75</x38>
			<y38>961.877757</y38>
			<x39>508.75</x39>
			<y39>968.651543</y39>
			<x40>500</x40>
			<y40>980.505671</y40>
			<x41>500</x41>
			<y41>990.666351</y41>
			<x42>508.75</x42>
			<y42>1002.520479</y42>
			<x43>515</x43>
			<y43>1004.213925</y43>
			<x44>511.25</x44>
			<y44>1009.294266</y44>
			<x45>481.25</x45>
			<y45>1012.681159</y45>
			<x46>465</x46>
			<y46>1031.309073</y46>
			<x47>465</x47>
			<y47>1048.243541</y47>
			<x48>476.25</x48>
			<y48>1063.484562</y48>
			<x49>488.75</x49>
			<y49>1066.871455</y49>
			<x50>490</x50>
			<y50>1075.338689</y50>
			<x51>486.25</x51>
			<y51>1080.419029</y51>
			<x52>476.25</x52>
			<y52>1083.805923</y52>
			<x53>450</x53>
			<y53>1112.594518</y53>
			<x54>447.5</x54>
			<y54>1119.368305</y54>
			<x55>447.5</x55>
			<y55>1132.915879</y55>
			<x56>435</x56>
			<y56>1163.397921</y56>
			<x57>435</x57>
			<y57>1176.945495</y57>
			<x58>427.5</x58>
			<y58>1200.653749</y58>
			<x59>427.5</x59>
			<y59>1214.201323</y59>
			<x60>425</x60>
			<y60>1217.588217</y60>
			<x61>425</x61>
			<y61>1254.844045</y61>
			<x62>428.75</x62>
			<y62>1259.924386</y62>
		</polygon>
	</object>
	<object>
		<name>T_L_R</name>
		<pose>Unspecified</pose>
		<truncated>0</truncated>
		<difficult>0</difficult>
		<occluded>0</occluded>
		<bndbox>
			<xmin>239</xmin>
			<xmax>499</xmax>
			<ymin>458</ymin>
			<ymax>628</ymax>
		</bndbox>
		<polygon>
			<x1>253.75</x1>
			<y1>613.027725</y1>
			<x2>258.75</x2>
			<y2>613.027725</y2>
			<x3>276.25</x3>
			<y3>623.188406</y3>
			<x4>283.75</x4>
			<y4>623.188406</y4>
			<x5>286.25</x5>
			<y5>626.5753</y5>
			<x6>321.25</x6>
			<y6>626.5753</y6>
			<x7>323.75</x7>
			<y7>623.188406</y7>
			<x8>331.25</x8>
			<y8>623.188406</y8>
			<x9>333.75</x9>
			<y9>619.801512</y9>
			<x10>351.25</x10>
			<y10>616.414618</y10>
			<x11>353.75</x11>
			<y11>613.027725</y11>
			<x12>388.75</x12>
			<y12>616.414618</y12>
			<x13>391.25</x13>
			<y13>613.027725</y13>
			<x14>403.75</x14>
			<y14>609.640832</y14>
			<x15>408.75</x15>
			<y15>602.867045</y15>
			<x16>418.75</x16>
			<y16>602.867045</y16>
			<x17>423.75</x17>
			<y17>609.640832</y17>
			<x18>433.75</x18>
			<y18>609.640832</y18>
			<x19>440</x19>
			<y19>601.173598</y19>
			<x20>442.5</x20>
			<y20>591.012918</y20>
			<x21>453.75</x21>
			<y21>582.545684</y21>
			<x22>462.5</x22>
			<y22>570.691556</y22>
			<x23>476.25</x23>
			<y23>538.516068</y23>
			<x24>483.75</x24>
			<y24>538.516068</y24>
			<x25>486.25</x25>
			<y25>535.129174</y25>
			<x26>491.25</x26>
			<y26>538.516068</y26>
			<x27>497.5</x27>
			<y27>533.435728</y27>
			<x28>491.25</x28>
			<y28>524.968494</y28>
			<x29>483.75</x29>
			<y29>521.581601</y29>
			<x30>475</x30>
			<y30>509.727473</y30>
			<x31>470</x31>
			<y31>496.179899</y31>
			<x32>470</x32>
			<y32>489.406112</y32>
			<x33>446.25</x33>
			<y33>460.617517</y33>
			<x34>441.25</x34>
			<y34>457.230624</y34>
			<x35>426.25</x35>
			<y35>457.230624</y35>
			<x36>422.5</x36>
			<y36>465.697857</y36>
			<x37>422.5</x37>
			<y37>482.632325</y37>
			<x38>418.75</x38>
			<y38>487.712665</y38>
			<x39>406.25</x39>
			<y39>480.938878</y39>
			<x40>386.25</x40>
			<y40>480.938878</y40>
			<x41>381.25</x41>
			<y41>477.551985</y41>
			<x42>378.75</x42>
			<y42>480.938878</y42>
			<x43>373.75</x43>
			<y43>480.938878</y43>
			<x44>363.75</x44>
			<y44>491.099559</y44>
			<x45>353.75</x45>
			<y45>491.099559</y45>
			<x46>348.75</x46>
			<y46>494.486453</y46>
			<x47>341.25</x47>
			<y47>508.034026</y47>
			<x48>331.25</x48>
			<y48>511.42092</y48>
			<x49>323.75</x49>
			<y49>518.194707</y49>
			<x50>311.25</x50>
			<y50>521.581601</y50>
			<x51>303.75</x51>
			<y51>531.742281</y51>
			<x52>291.25</x52>
			<y52>538.516068</y52>
			<x53>276.25</x53>
			<y53>552.063642</y53>
			<x54>271.25</x54>
			<y54>552.063642</y54>
			<x55>256.25</x55>
			<y55>568.99811</y55>
			<x56>241.25</x56>
			<y56>579.15879</y56>
			<x57>237.5</x57>
			<y57>584.23913</y57>
			<x58>237.5</x58>
			<y58>594.399811</y58>
			<x59>246.25</x59>
			<y59>606.253938</y59>
			<x60>253.75</x60>
			<y60>613.027725</y60>
		</polygon>
	</object>
	<object>
		<name>T_L_R</name>
		<pose>Unspecified</pose>
		<truncated>0</truncated>
		<difficult>0</difficult>
		<occluded>0</occluded>
		<bndbox>
			<xmin>744</xmin>
			<xmax>954</xmax>
			<ymin>851</ymin>
			<ymax>1044</ymax>
		</bndbox>
		<polygon>
			<x1>757.5</x1>
			<y1>916.154694</y1>
			<x2>757.5</x2>
			<y2>926.315375</y2>
			<x3>767.5</x3>
			<y3>953.410523</y3>
			<x4>782.5</x4>
			<y4>973.731884</y4>
			<x5>787.5</x5>
			<y5>987.279458</y5>
			<x6>791.25</x6>
			<y6>992.359799</y6>
			<x7>801.25</x7>
			<y7>988.972905</y7>
			<x8>810</x8>
			<y8>1010.987713</y8>
			<x9>828.75</x9>
			<y9>1033.002521</y9>
			<x10>836.25</x10>
			<y10>1033.002521</y10>
			<x11>838.75</x11>
			<y11>1036.389414</y11>
			<x12>843.75</x12>
			<y12>1033.002521</y12>
			<x13>845</x13>
			<y13>1014.374606</y13>
			<x14>848.75</x14>
			<y14>1012.681159</y14>
			<x15>863.75</x15>
			<y15>1036.389414</y15>
			<x16>873.75</x16>
			<y16>1043.163201</y16>
			<x17>903.75</x17>
			<y17>1043.163201</y17>
			<x18>921.25</x18>
			<y18>1033.002521</y18>
			<x19>952.5</x19>
			<y19>987.279458</y19>
			<x20>951.25</x20>
			<y20>982.199118</y20>
			<x21>943.75</x21>
			<y21>982.199118</y21>
			<x22>941.25</x22>
			<y22>978.812225</y22>
			<x23>916.25</x23>
			<y23>978.812225</y23>
			<x24>898.75</x24>
			<y24>961.877757</y24>
			<x25>881.25</x25>
			<y25>938.169502</y25>
			<x26>868.75</x26>
			<y26>931.395715</y26>
			<x27>866.25</x27>
			<y27>914.461247</y27>
			<x28>853.75</x28>
			<y28>907.687461</y28>
			<x29>838.75</x29>
			<y29>907.687461</y29>
			<x30>835</x30>
			<y30>902.60712</y30>
			<x31>842.5</x31>
			<y31>875.511972</y31>
			<x32>842.5</x32>
			<y32>855.190611</y32>
			<x33>838.75</x33>
			<y33>850.110271</y33>
			<x34>823.75</x34>
			<y34>860.270951</y34>
			<x35>803.75</x35>
			<y35>860.270951</y35>
			<x36>801.25</x36>
			<y36>856.884058</y36>
			<x37>778.75</x37>
			<y37>856.884058</y37>
			<x38>776.25</x38>
			<y38>853.497164</y38>
			<x39>766.25</x39>
			<y39>853.497164</y39>
			<x40>750</x40>
			<y40>872.125079</y40>
			<x41>747.5</x41>
			<y41>892.44644</y41>
			<x42>742.5</x42>
			<y42>899.220227</y42>
			<x43>742.5</x43>
			<y43>905.994014</y43>
			<x44>757.5</x44>
			<y44>916.154694</y44>
		</polygon>
	</object>
	<object>
		<name>T_L_R</name>
		<pose>Unspecified</pose>
		<truncated>0</truncated>
		<difficult>0</difficult>
		<occluded>0</occluded>
		<bndbox>
			<xmin>871</xmin>
			<xmax>979</xmax>
			<ymin>682</ymin>
			<ymax>973</ymax>
		</bndbox>
		<polygon>
			<x1>872.5</x1>
			<y1>811.160996</y1>
			<x2>870</x2>
			<y2>814.547889</y2>
			<x3>872.5</x3>
			<y3>831.482357</y3>
			<x4>878.75</x4>
			<y4>839.94959</y4>
			<x5>883.75</x5>
			<y5>839.94959</y5>
			<x6>886.25</x6>
			<y6>843.336484</y6>
			<x7>896.25</x7>
			<y7>839.94959</y7>
			<x8>901.25</x8>
			<y8>833.175803</y8>
			<x9>905</x9>
			<y9>834.86925</y9>
			<x10>907.5</x10>
			<y10>851.803718</y10>
			<x11>917.5</x11>
			<y11>872.125079</y11>
			<x12>917.5</x12>
			<y12>882.285759</y12>
			<x13>922.5</x13>
			<y13>892.44644</y13>
			<x14>922.5</x14>
			<y14>899.220227</y14>
			<x15>927.5</x15>
			<y15>905.994014</y15>
			<x16>930</x16>
			<y16>919.541588</y16>
			<x17>937.5</x17>
			<y17>933.089162</y17>
			<x18>937.5</x18>
			<y18>939.862949</y18>
			<x19>963.75</x19>
			<y19>972.038437</y19>
			<x20>971.25</x20>
			<y20>972.038437</y20>
			<x21>970</x21>
			<y21>824.70857</y21>
			<x22>975</x22>
			<y22>817.934783</y22>
			<x23>977.5</x23>
			<y23>807.774102</y23>
			<x24>972.5</x24>
			<y24>801.000315</y24>
			<x25>965</x25>
			<y25>780.678954</y25>
			<x26>965</x26>
			<y26>773.905167</y26>
			<x27>976.25</x27>
			<y27>765.437934</y27>
			<x28>977.5</x28>
			<y28>760.357593</y28>
			<x29>960</x29>
			<y29>740.036232</y29>
			<x30>960</x30>
			<y30>733.262445</y30>
			<x31>943.75</x31>
			<y31>704.47385</y31>
			<x32>936.25</x32>
			<y32>697.700063</y32>
			<x33>918.75</x33>
			<y33>690.926276</y33>
			<x34>908.75</x34>
			<y34>680.765596</y34>
			<x35>902.5</x35>
			<y35>682.459042</y35>
			<x36>895</x36>
			<y36>709.55419</y36>
			<x37>882.5</x37>
			<y37>729.875552</y37>
			<x38>882.5</x38>
			<y38>750.196912</y38>
			<x39>890</x39>
			<y39>767.13138</y39>
			<x40>872.5</x40>
			<y40>801.000315</y40>
			<x41>872.5</x41>
			<y41>811.160996</y41>
		</polygon>
	</object>
	<object>
		<name>T_L_R</name>
		<pose>Unspecified</pose>
		<truncated>0</truncated>
		<difficult>0</difficult>
		<occluded>0</occluded>
		<bndbox>
			<xmin>499</xmin>
			<xmax>679</xmax>
			<ymin>624</ymin>
			<ymax>743</ymax>
		</bndbox>
		<polygon>
			<x1>497.5</x1>
			<y1>689.23283</y1>
			<x2>503.75</x2>
			<y2>694.31317</y2>
			<x3>506.25</x3>
			<y3>690.926276</y3>
			<x4>508.75</x4>
			<y4>694.31317</y4>
			<x5>523.75</x5>
			<y5>694.31317</y5>
			<x6>530</x6>
			<y6>706.167296</y6>
			<x7>551.25</x7>
			<y7>731.568998</y7>
			<x8>558.75</x8>
			<y8>731.568998</y8>
			<x9>571.25</x9>
			<y9>738.342786</y9>
			<x10>581.25</x10>
			<y10>738.342786</y10>
			<x11>583.75</x11>
			<y11>741.729678</y11>
			<x12>633.75</x12>
			<y12>741.729678</y12>
			<x13>636.25</x13>
			<y13>738.342786</y13>
			<x14>648.75</x14>
			<y14>734.955892</y14>
			<x15>661.25</x15>
			<y15>724.795211</y15>
			<x16>677.5</x16>
			<y16>699.39351</y16>
			<x17>677.5</x17>
			<y17>692.619722</y17>
			<x18>663.75</x18>
			<y18>677.378702</y18>
			<x19>623.75</x19>
			<y19>650.283554</y19>
			<x20>618.75</x20>
			<y20>650.283554</y20>
			<x21>613.75</x21>
			<y21>643.509766</y21>
			<x22>615</x22>
			<y22>635.042533</y22>
			<x23>611.25</x23>
			<y23>629.962193</y23>
			<x24>606.25</x24>
			<y24>629.962193</y24>
			<x25>603.75</x25>
			<y25>633.349086</y25>
			<x26>591.25</x26>
			<y26>633.349086</y26>
			<x27>588.75</x27>
			<y27>629.962193</y27>
			<x28>586.25</x28>
			<y28>633.349086</y28>
			<x29>576.25</x29>
			<y29>633.349086</y29>
			<x30>573.75</x30>
			<y30>629.962193</y30>
			<x31>561.25</x31>
			<y31>629.962193</y31>
			<x32>553.75</x32>
			<y32>623.188406</y32>
			<x33>546.25</x33>
			<y33>623.188406</y33>
			<x34>530</x34>
			<y34>641.81632</y34>
			<x35>527.5</x35>
			<y35>651.977</y35>
			<x36>522.5</x36>
			<y36>658.750788</y36>
			<x37>520</x37>
			<y37>672.298362</y37>
			<x38>497.5</x38>
			<y38>689.23283</y38>
		</polygon>
	</object>
	<object>
		<name>T_L_H</name>
		<pose>Unspecified</pose>
		<truncated>0</truncated>
		<difficult>0</difficult>
		<occluded>0</occluded>
		<bndbox>
			<xmin>1</xmin>
			<xmax>144</xmax>
			<ymin>1</ymin>
			<ymax>170</ymax>
		</bndbox>
		<polygon>
			<x1>23.75</x1>
			<y1>84.672338</y1>
			<x2>27.5</x2>
			<y2>103.300252</y2>
			<x3>33.75</x3>
			<y3>115.15438</y3>
			<x4>41.25</x4>
			<y4>115.15438</y4>
			<x5>46.25</x5>
			<y5>108.380592</y5>
			<x6>53.75</x6>
			<y6>108.380592</y6>
			<x7>55</x7>
			<y7>113.460932</y7>
			<x8>68.75</x8>
			<y8>132.088847</y8>
			<x9>88.75</x9>
			<y9>145.636421</y9>
			<x10>93.75</x10>
			<y10>145.636421</y10>
			<x11>108.75</x11>
			<y11>159.183995</y11>
			<x12>113.75</x12>
			<y12>159.183995</y12>
			<x13>121.25</x13>
			<y13>165.957782</y13>
			<x14>128.75</x14>
			<y14>165.957782</y14>
			<x15>131.25</x15>
			<y15>169.344676</y15>
			<x16>142.5</x16>
			<y16>167.651229</y16>
			<x17>142.5</x17>
			<y17>154.103655</y17>
			<x18>140</x18>
			<y18>150.716761</y18>
			<x19>140</x19>
			<y19>140.556081</y19>
			<x20>142.5</x20>
			<y20>137.169187</y20>
			<x21>140</x21>
			<y21>99.913358</y21>
			<x22>132.5</x22>
			<y22>82.978891</y22>
			<x23>132.5</x23>
			<y23>69.431317</y23>
			<x24>125</x24>
			<y24>59.270636</y24>
			<x25>125</x25>
			<y25>49.109956</y25>
			<x26>128.75</x26>
			<y26>47.416509</y26>
			<x27>132.5</x27>
			<y27>38.949276</y27>
			<x28>120</x28>
			<y28>28.788595</y28>
			<x29>123.75</x29>
			<y29>23.708254</y29>
			<x30>126.25</x30>
			<y30>27.095148</y30>
			<x31>130</x31>
			<y31>22.014808</y31>
			<x32>130</x32>
			<y32>15.24102</y32>
			<x33>121.25</x33>
			<y33>0</y33>
			<x34>5</x34>
			<y34>1.693446</y34>
			<x35>0</x35>
			<y35>11.854128</y35>
			<x36>1.25</x36>
			<y36>94.833018</y36>
			<x37>13.75</x37>
			<y37>84.672338</y37>
			<x38>23.75</x38>
			<y38>84.672338</y38>
		</polygon>
	</object>
</annotation>
