<annotation>
	<folder></folder>
	<filename>00154_jpg.rf.ee57adf34b13e70c28182cf61241258c.jpg</filename>
	<path>00154_jpg.rf.ee57adf34b13e70c28182cf61241258c.jpg</path>
	<source>
		<database>roboflow.com</database>
	</source>
	<size>
		<width>640</width>
		<height>640</height>
		<depth>3</depth>
	</size>
	<segmented>0</segmented>
	<object>
		<name>T_L_H</name>
		<pose>Unspecified</pose>
		<truncated>0</truncated>
		<difficult>0</difficult>
		<occluded>0</occluded>
		<bndbox>
			<xmin>298</xmin>
			<xmax>446</xmax>
			<ymin>486</ymin>
			<ymax>614</ymax>
		</bndbox>
		<polygon>
			<x1>445.2</x1>
			<y1>592.266667</y1>
			<x2>434.2</x2>
			<y2>580.8</y2>
			<x3>419.8</x3>
			<y3>570.133333</y3>
			<x4>406.2</x4>
			<y4>546.133333</y4>
			<x5>395.4</x5>
			<y5>539.2</y5>
			<x6>385.8</x6>
			<y6>529.6</y6>
			<x7>372.6</x7>
			<y7>525.333333</y7>
			<x8>364.6</x8>
			<y8>518.4</y8>
			<x9>356.2</x9>
			<y9>516.266667</y9>
			<x10>355.6</x10>
			<y10>508.533333</y10>
			<x11>346.2</x11>
			<y11>505.6</y11>
			<x12>344</x12>
			<y12>498.933333</y12>
			<x13>340.2</x13>
			<y13>494.4</y13>
			<x14>324.6</x14>
			<y14>490.666667</y14>
			<x15>318.6</x15>
			<y15>484.8</y15>
			<x16>305.8</x16>
			<y16>486.4</y16>
			<x17>300.8</x17>
			<y17>490.4</y17>
			<x18>297.2</x18>
			<y18>501.6</y18>
			<x19>298.8</x19>
			<y19>508.533333</y19>
			<x20>298.8</x20>
			<y20>521.333333</y20>
			<x21>312.4</x21>
			<y21>559.2</y21>
			<x22>323.4</x22>
			<y22>575.466667</y22>
			<x23>343.8</x23>
			<y23>588.8</y23>
			<x24>356.2</x24>
			<y24>599.466667</y24>
			<x25>374.2</x25>
			<y25>602.133333</y25>
			<x26>385.8</x26>
			<y26>610.133333</y26>
			<x27>393.8</x27>
			<y27>612.8</y27>
			<x28>406.8</x28>
			<y28>613.066667</y28>
			<x29>433</x29>
			<y29>605.866667</y29>
			<x30>441.8</x30>
			<y30>599.466667</y30>
			<x31>445.2</x31>
			<y31>595.466667</y31>
			<x32>445.2</x32>
			<y32>592.266667</y32>
		</polygon>
	</object>
	<object>
		<name>T_L_H</name>
		<pose>Unspecified</pose>
		<truncated>0</truncated>
		<difficult>0</difficult>
		<occluded>0</occluded>
		<bndbox>
			<xmin>135</xmin>
			<xmax>274</xmax>
			<ymin>440</ymin>
			<ymax>503</ymax>
		</bndbox>
		<polygon>
			<x1>264.6</x1>
			<y1>474.133333</y1>
			<x2>273.2</x2>
			<y2>468</y2>
			<x3>273.2</x3>
			<y3>461.066667</y3>
			<x4>270</x4>
			<y4>450.4</y4>
			<x5>260.6</x5>
			<y5>440.533333</y5>
			<x6>249.8</x6>
			<y6>441.6</y6>
			<x7>243</x7>
			<y7>438.933333</y7>
			<x8>240.8</x8>
			<y8>441.333333</y8>
			<x9>238.4</x9>
			<y9>449.866667</y9>
			<x10>235.8</x10>
			<y10>451.733333</y10>
			<x11>222.6</x11>
			<y11>451.2</y11>
			<x12>215</x12>
			<y12>454.933333</y12>
			<x13>209.4</x13>
			<y13>453.866667</y13>
			<x14>203.4</x14>
			<y14>449.6</y14>
			<x15>195.4</x15>
			<y15>452.8</y15>
			<x16>162.2</x16>
			<y16>450.133333</y16>
			<x17>153</x17>
			<y17>455.466667</y17>
			<x18>140.6</x18>
			<y18>457.6</y18>
			<x19>134</x19>
			<y19>465.333333</y19>
			<x20>135.2</x20>
			<y20>473.866667</y20>
			<x21>141</x21>
			<y21>480.533333</y21>
			<x22>165</x22>
			<y22>494.933333</y22>
			<x23>175</x23>
			<y23>496</y23>
			<x24>189.4</x24>
			<y24>493.866667</y24>
			<x25>205.4</x25>
			<y25>500.8</y25>
			<x26>216</x26>
			<y26>501.6</y26>
			<x27>235.8</x27>
			<y27>492.266667</y27>
			<x28>245.8</x28>
			<y28>490.666667</y28>
			<x29>257.4</x29>
			<y29>484.266667</y29>
			<x30>264.6</x30>
			<y30>474.133333</y30>
		</polygon>
	</object>
	<object>
		<name>T_L_H</name>
		<pose>Unspecified</pose>
		<truncated>0</truncated>
		<difficult>0</difficult>
		<occluded>0</occluded>
		<bndbox>
			<xmin>207</xmin>
			<xmax>298</xmax>
			<ymin>293</ymin>
			<ymax>368</ymax>
		</bndbox>
		<polygon>
			<x1>297.2</x1>
			<y1>342.666667</y1>
			<x2>293</x2>
			<y2>335.466667</y2>
			<x3>285</x3>
			<y3>330.133333</y3>
			<x4>273.8</x4>
			<y4>317.333333</y4>
			<x5>266.6</x5>
			<y5>305.066667</y5>
			<x6>255.8</x6>
			<y6>298.133333</y6>
			<x7>251</x7>
			<y7>291.733333</y7>
			<x8>236.6</x8>
			<y8>294.4</y8>
			<x9>233.2</x9>
			<y9>297.866667</y9>
			<x10>231</x10>
			<y10>306.133333</y10>
			<x11>220.2</x11>
			<y11>306.133333</y11>
			<x12>210.2</x12>
			<y12>309.866667</y12>
			<x13>206.4</x13>
			<y13>313.866667</y13>
			<x14>207.4</x14>
			<y14>316.8</y14>
			<x15>217.8</x15>
			<y15>322.666667</y15>
			<x16>228.2</x16>
			<y16>332.8</y16>
			<x17>235</x17>
			<y17>334.933333</y17>
			<x18>243.4</x18>
			<y18>340.8</y18>
			<x19>247.6</x19>
			<y19>352.266667</y19>
			<x20>255.8</x20>
			<y20>366.933333</y20>
			<x21>274</x21>
			<y21>367.2</y21>
			<x22>288.2</x22>
			<y22>363.2</y22>
			<x23>291.2</x23>
			<y23>354.933333</y23>
			<x24>296.8</x24>
			<y24>349.6</y24>
			<x25>297.2</x25>
			<y25>342.666667</y25>
		</polygon>
	</object>
	<object>
		<name>T_L_H</name>
		<pose>Unspecified</pose>
		<truncated>0</truncated>
		<difficult>0</difficult>
		<occluded>0</occluded>
		<bndbox>
			<xmin>333</xmin>
			<xmax>447</xmax>
			<ymin>366</ymin>
			<ymax>428</ymax>
		</bndbox>
		<polygon>
			<x1>438.6</x1>
			<y1>397.333333</y1>
			<x2>445.6</x2>
			<y2>392.266667</y2>
			<x3>445.6</x3>
			<y3>385.333333</y3>
			<x4>434.2</x4>
			<y4>373.333333</y4>
			<x5>419.8</x5>
			<y5>372.8</y5>
			<x6>418.4</x6>
			<y6>377.866667</y6>
			<x7>420</x7>
			<y7>384.8</y7>
			<x8>416.2</x8>
			<y8>390.4</y8>
			<x9>407.2</x9>
			<y9>381.6</y9>
			<x10>401.4</x10>
			<y10>366.933333</y10>
			<x11>393</x11>
			<y11>366.933333</y11>
			<x12>390.8</x12>
			<y12>368.8</y12>
			<x13>389</x13>
			<y13>374.933333</y13>
			<x14>377</x14>
			<y14>374.933333</y14>
			<x15>367</x15>
			<y15>368</y15>
			<x16>358.6</x16>
			<y16>369.6</y16>
			<x17>353.4</x17>
			<y17>364.8</y17>
			<x18>346.6</x18>
			<y18>366.933333</y18>
			<x19>340.6</x19>
			<y19>365.333333</y19>
			<x20>334</x20>
			<y20>373.066667</y20>
			<x21>331.6</x21>
			<y21>377.866667</y21>
			<x22>331.6</x22>
			<y22>382.133333</y22>
			<x23>336.4</x23>
			<y23>390.666667</y23>
			<x24>334.4</x24>
			<y24>397.6</y24>
			<x25>339.4</x25>
			<y25>405.333333</y25>
			<x26>361</x26>
			<y26>416.533333</y26>
			<x27>366.6</x27>
			<y27>422.4</y27>
			<x28>374.2</x28>
			<y28>426.666667</y28>
			<x29>386.4</x29>
			<y29>427.466667</y29>
			<x30>395.8</x30>
			<y30>424</y30>
			<x31>407.4</x31>
			<y31>427.2</y31>
			<x32>421</x32>
			<y32>420.266667</y32>
			<x33>438.6</x33>
			<y33>397.333333</y33>
		</polygon>
	</object>
	<object>
		<name>T_L_R</name>
		<pose>Unspecified</pose>
		<truncated>0</truncated>
		<difficult>0</difficult>
		<occluded>0</occluded>
		<bndbox>
			<xmin>397</xmin>
			<xmax>503</xmax>
			<ymin>166</ymin>
			<ymax>249</ymax>
		</bndbox>
		<polygon>
			<x1>442.2</x1>
			<y1>226.666667</y1>
			<x2>464.2</x2>
			<y2>208</y2>
			<x3>481</x3>
			<y3>200</y3>
			<x4>484.2</x4>
			<y4>194.133333</y4>
			<x5>494.6</x5>
			<y5>193.6</y5>
			<x6>501</x6>
			<y6>190.933333</y6>
			<x7>502.4</x7>
			<y7>187.466667</y7>
			<x8>501.6</x8>
			<y8>181.066667</y8>
			<x9>493</x9>
			<y9>171.733333</y9>
			<x10>474.2</x10>
			<y10>165.333333</y10>
			<x11>467.4</x11>
			<y11>168</y11>
			<x12>461.4</x12>
			<y12>173.333333</y12>
			<x13>449.8</x13>
			<y13>176</y13>
			<x14>447</x14>
			<y14>179.2</y14>
			<x15>434.2</x15>
			<y15>185.066667</y15>
			<x16>429</x16>
			<y16>184</y16>
			<x17>419.8</x17>
			<y17>193.066667</y17>
			<x18>411.4</x18>
			<y18>190.4</y18>
			<x19>406.8</x19>
			<y19>200.266667</y19>
			<x20>403.2</x20>
			<y20>203.466667</y20>
			<x21>402</x21>
			<y21>228.533333</y21>
			<x22>395.6</x22>
			<y22>240.8</y22>
			<x23>397</x23>
			<y23>244.266667</y23>
			<x24>403</x24>
			<y24>248</y24>
			<x25>408.8</x25>
			<y25>247.733333</y25>
			<x26>420.2</x26>
			<y26>244.8</y26>
			<x27>429.4</x27>
			<y27>246.4</y27>
			<x28>442.8</x28>
			<y28>233.866667</y28>
			<x29>442.2</x29>
			<y29>226.666667</y29>
		</polygon>
	</object>
	<object>
		<name>T_L_H</name>
		<pose>Unspecified</pose>
		<truncated>0</truncated>
		<difficult>0</difficult>
		<occluded>0</occluded>
		<bndbox>
			<xmin>226</xmin>
			<xmax>309</xmax>
			<ymin>534</ymin>
			<ymax>641</ymax>
		</bndbox>
		<polygon>
			<x1>294.375</x1>
			<y1>638.333333</y1>
			<x2>295.625</x2>
			<y2>640</y2>
			<x3>296.875</x3>
			<y3>638.333333</y3>
			<x4>305.625</x4>
			<y4>638.333333</y4>
			<x5>307.5</x5>
			<y5>635.833333</y5>
			<x6>307.5</x6>
			<y6>630.833333</y6>
			<x7>297.5</x7>
			<y7>612.5</y7>
			<x8>296.25</x8>
			<y8>607.5</y8>
			<x9>297.5</x9>
			<y9>605.833333</y9>
			<x10>297.5</x10>
			<y10>595.833333</y10>
			<x11>295</x11>
			<y11>587.5</y11>
			<x12>283.125</x12>
			<y12>571.666667</y12>
			<x13>280.625</x13>
			<y13>570</y13>
			<x14>274.375</x14>
			<y14>571.666667</y14>
			<x15>272.5</x15>
			<y15>565.833333</y15>
			<x16>267.5</x16>
			<y16>560.833333</y16>
			<x17>267.5</x17>
			<y17>557.5</y17>
			<x18>262.5</x18>
			<y18>552.5</y18>
			<x19>260</x19>
			<y19>539.166667</y19>
			<x20>255.625</x20>
			<y20>535</y20>
			<x21>249.375</x21>
			<y21>533.333333</y21>
			<x22>246.25</x22>
			<y22>540.833333</y22>
			<x23>235</x23>
			<y23>552.5</y23>
			<x24>241.875</x24>
			<y24>561.666667</y24>
			<x25>235</x25>
			<y25>569.166667</y25>
			<x26>233.75</x26>
			<y26>582.5</y26>
			<x27>227.5</x27>
			<y27>597.5</y27>
			<x28>227.5</x28>
			<y28>620.833333</y28>
			<x29>225</x29>
			<y29>634.166667</y29>
			<x30>226.875</x30>
			<y30>638.333333</y30>
			<x31>294.375</x31>
			<y31>638.333333</y31>
		</polygon>
	</object>
	<object>
		<name>T_L_R</name>
		<pose>Unspecified</pose>
		<truncated>0</truncated>
		<difficult>0</difficult>
		<occluded>0</occluded>
		<bndbox>
			<xmin>426</xmin>
			<xmax>505</xmax>
			<ymin>321</ymin>
			<ymax>419</ymax>
		</bndbox>
		<polygon>
			<x1>438.75</x1>
			<y1>379.166667</y1>
			<x2>446.25</x2>
			<y2>385.833333</y2>
			<x3>446.25</x3>
			<y3>394.166667</y3>
			<x4>455</x4>
			<y4>405.833333</y4>
			<x5>459.375</x5>
			<y5>415</y5>
			<x6>470.625</x6>
			<y6>415</y6>
			<x7>476.875</x7>
			<y7>418.333333</y7>
			<x8>483.125</x8>
			<y8>413.333333</y8>
			<x9>496.875</x9>
			<y9>408.333333</y9>
			<x10>503.75</x10>
			<y10>400.833333</y10>
			<x11>503.75</x11>
			<y11>392.5</y11>
			<x12>488.75</x12>
			<y12>379.166667</y12>
			<x13>488.75</x13>
			<y13>367.5</y13>
			<x14>485</x14>
			<y14>360.833333</y14>
			<x15>483.125</x15>
			<y15>358.333333</y15>
			<x16>476.875</x16>
			<y16>358.333333</y16>
			<x17>472.5</x17>
			<y17>352.5</y17>
			<x18>471.25</x18>
			<y18>337.5</y18>
			<x19>468.125</x19>
			<y19>333.333333</y19>
			<x20>465.625</x20>
			<y20>333.333333</y20>
			<x21>456.875</x21>
			<y21>321.666667</y21>
			<x22>441.875</x22>
			<y22>320</y22>
			<x23>430.625</x23>
			<y23>333.333333</y23>
			<x24>426.875</x24>
			<y24>335</y24>
			<x25>425</x25>
			<y25>337.5</y25>
			<x26>425</x26>
			<y26>352.5</y26>
			<x27>435</x27>
			<y27>364.166667</y27>
			<x28>438.75</x28>
			<y28>379.166667</y28>
		</polygon>
	</object>
	<object>
		<name>T_S_H</name>
		<pose>Unspecified</pose>
		<truncated>0</truncated>
		<difficult>0</difficult>
		<occluded>0</occluded>
		<bndbox>
			<xmin>269</xmin>
			<xmax>336</xmax>
			<ymin>318</ymin>
			<ymax>561</ymax>
		</bndbox>
		<polygon>
			<x1>277.5</x1>
			<y1>545.833333</y1>
			<x2>277.5</x2>
			<y2>539.166667</y2>
			<x3>281.25</x3>
			<y3>525.833333</y3>
			<x4>282.5</x4>
			<y4>514.166667</y4>
			<x5>286.25</x5>
			<y5>504.166667</y5>
			<x6>287.5</x6>
			<y6>489.166667</y6>
			<x7>292.5</x7>
			<y7>480.833333</y7>
			<x8>306.25</x8>
			<y8>422.5</y8>
			<x9>311.25</x9>
			<y9>407.5</y9>
			<x10>311.25</x10>
			<y10>402.5</y10>
			<x11>315</x11>
			<y11>394.166667</y11>
			<x12>318.75</x12>
			<y12>370.833333</y12>
			<x13>321.25</x13>
			<y13>367.5</y13>
			<x14>330</x14>
			<y14>335.833333</y14>
			<x15>335</x15>
			<y15>324.166667</y15>
			<x16>335</x16>
			<y16>319.166667</y16>
			<x17>333.125</x17>
			<y17>316.666667</y17>
			<x18>323.75</x18>
			<y18>322.5</y18>
			<x19>318.75</x19>
			<y19>342.5</y19>
			<x20>315</x20>
			<y20>350.833333</y20>
			<x21>315</x21>
			<y21>359.166667</y21>
			<x22>311.25</x22>
			<y22>364.166667</y22>
			<x23>297.5</x23>
			<y23>422.5</y23>
			<x24>292.5</x24>
			<y24>435.833333</y24>
			<x25>287.5</x25>
			<y25>455.833333</y25>
			<x26>287.5</x26>
			<y26>462.5</y26>
			<x27>285</x27>
			<y27>467.5</y27>
			<x28>285</x28>
			<y28>472.5</y28>
			<x29>278.75</x29>
			<y29>494.166667</y29>
			<x30>272.5</x30>
			<y30>529.166667</y30>
			<x31>268.75</x31>
			<y31>540.833333</y31>
			<x32>267.5</x32>
			<y32>552.5</y32>
			<x33>268.75</x33>
			<y33>557.5</y33>
			<x34>273.125</x34>
			<y34>560</y34>
			<x35>277.5</x35>
			<y35>545.833333</y35>
		</polygon>
	</object>
	<object>
		<name>T_L_R</name>
		<pose>Unspecified</pose>
		<truncated>0</truncated>
		<difficult>0</difficult>
		<occluded>0</occluded>
		<bndbox>
			<xmin>279</xmin>
			<xmax>334</xmax>
			<ymin>193</ymin>
			<ymax>241</ymax>
		</bndbox>
		<polygon>
			<x1>303.125</x1>
			<y1>230</y1>
			<x2>306.875</x2>
			<y2>233.333333</y2>
			<x3>316.875</x3>
			<y3>233.333333</y3>
			<x4>321.875</x4>
			<y4>228.333333</y4>
			<x5>326.875</x5>
			<y5>228.333333</y5>
			<x6>330</x6>
			<y6>222.5</y6>
			<x7>330</x7>
			<y7>214.166667</y7>
			<x8>332.5</x8>
			<y8>210.833333</y8>
			<x9>326.25</x9>
			<y9>205.833333</y9>
			<x10>325</x10>
			<y10>199.166667</y10>
			<x11>320.625</x11>
			<y11>193.333333</y11>
			<x12>311.875</x12>
			<y12>191.666667</y12>
			<x13>296.875</x13>
			<y13>196.666667</y13>
			<x14>291.25</x14>
			<y14>202.5</y14>
			<x15>290</x15>
			<y15>207.5</y15>
			<x16>283.75</x16>
			<y16>215.833333</y16>
			<x17>282.5</x17>
			<y17>225.833333</y17>
			<x18>277.5</x18>
			<y18>234.166667</y18>
			<x19>279.375</x19>
			<y19>240</y19>
			<x20>303.125</x20>
			<y20>230</y20>
		</polygon>
	</object>
	<object>
		<name>T_L_R</name>
		<pose>Unspecified</pose>
		<truncated>0</truncated>
		<difficult>0</difficult>
		<occluded>0</occluded>
		<bndbox>
			<xmin>334</xmin>
			<xmax>416</xmax>
			<ymin>128</ymin>
			<ymax>166</ymax>
		</bndbox>
		<polygon>
			<x1>349.375</x1>
			<y1>163.333333</y1>
			<x2>354.375</x2>
			<y2>156.666667</y2>
			<x3>360.625</x3>
			<y3>156.666667</y3>
			<x4>361.875</x4>
			<y4>158.333333</y4>
			<x5>385.625</x5>
			<y5>156.666667</y5>
			<x6>388.75</x6>
			<y6>159.166667</y6>
			<x7>387.5</x7>
			<y7>160.833333</y7>
			<x8>390.625</x8>
			<y8>165</y8>
			<x9>410.625</x9>
			<y9>165</y9>
			<x10>415</x10>
			<y10>160.833333</y10>
			<x11>415</x11>
			<y11>155.833333</y11>
			<x12>408.75</x12>
			<y12>142.5</y12>
			<x13>394.375</x13>
			<y13>133.333333</y13>
			<x14>364.375</x14>
			<y14>126.666667</y14>
			<x15>354.375</x15>
			<y15>131.666667</y15>
			<x16>336.875</x16>
			<y16>133.333333</y16>
			<x17>335</x17>
			<y17>135.833333</y17>
			<x18>335</x18>
			<y18>147.5</y18>
			<x19>332.5</x19>
			<y19>152.5</y19>
			<x20>344.375</x20>
			<y20>161.666667</y20>
			<x21>349.375</x21>
			<y21>163.333333</y21>
		</polygon>
	</object>
</annotation>
